{
"meta":{"test_sets":[],"test_metrics":[],"learn_metrics":[{"best_value":"Min","name":"RMSE"}],"launch_mode":"Train","parameters":"","iteration_count":1000,"learn_sets":["learn"],"name":"experiment"},
"iterations":[
{"learn":[14.59871775],"iteration":0,"passed_time":0.1331004354,"remaining_time":132.967335},
{"learn":[14.22518863],"iteration":1,"passed_time":0.1338444506,"remaining_time":66.78838087},
{"learn":[13.8866124],"iteration":2,"passed_time":0.1346092089,"remaining_time":44.7351271},
{"learn":[13.52356875],"iteration":3,"passed_time":0.1355437688,"remaining_time":33.75039842},
{"learn":[13.18870211],"iteration":4,"passed_time":0.1363909477,"remaining_time":27.14179859},
{"learn":[12.9124226],"iteration":5,"passed_time":0.137504772,"remaining_time":22.77995723},
{"learn":[12.60003351],"iteration":6,"passed_time":0.1383303914,"remaining_time":19.62315409},
{"learn":[12.32990573],"iteration":7,"passed_time":0.1391366701,"remaining_time":17.25294709},
{"learn":[12.0660619],"iteration":8,"passed_time":0.1397898501,"remaining_time":15.39241571},
{"learn":[11.77309809],"iteration":9,"passed_time":0.1405467118,"remaining_time":13.91412446},
{"learn":[11.49227636],"iteration":10,"passed_time":0.1413146981,"remaining_time":12.70547603},
{"learn":[11.26264833],"iteration":11,"passed_time":0.1420204779,"remaining_time":11.69301935},
{"learn":[11.04260393],"iteration":12,"passed_time":0.1428168054,"remaining_time":10.8430913},
{"learn":[10.79916926],"iteration":13,"passed_time":0.143831725,"remaining_time":10.12986292},
{"learn":[10.5541002],"iteration":14,"passed_time":0.1447923885,"remaining_time":9.508033509},
{"learn":[10.31918115],"iteration":15,"passed_time":0.1458104863,"remaining_time":8.967344909},
{"learn":[10.10004441],"iteration":16,"passed_time":0.1467387533,"remaining_time":8.484952618},
{"learn":[9.894556723],"iteration":17,"passed_time":0.1477452807,"remaining_time":8.060325868},
{"learn":[9.690174082],"iteration":18,"passed_time":0.1488214667,"remaining_time":7.683887308},
{"learn":[9.506034866],"iteration":19,"passed_time":0.1500829737,"remaining_time":7.354065711},
{"learn":[9.338524633],"iteration":20,"passed_time":0.1508893319,"remaining_time":7.034316948},
{"learn":[9.170203312],"iteration":21,"passed_time":0.15169336,"remaining_time":6.743459367},
{"learn":[9.010299969],"iteration":22,"passed_time":0.1524517205,"remaining_time":6.475883955},
{"learn":[8.843866678],"iteration":23,"passed_time":0.153086982,"remaining_time":6.225537268},
{"learn":[8.690548059],"iteration":24,"passed_time":0.1537098499,"remaining_time":5.994684144},
{"learn":[8.555307687],"iteration":25,"passed_time":0.1543474888,"remaining_time":5.782094389},
{"learn":[8.413851302],"iteration":26,"passed_time":0.1551435613,"remaining_time":5.590914265},
{"learn":[8.29256019],"iteration":27,"passed_time":0.1559879327,"remaining_time":5.415009663},
{"learn":[8.162193833],"iteration":28,"passed_time":0.1566422983,"remaining_time":5.244816264},
{"learn":[8.040736294],"iteration":29,"passed_time":0.1575212693,"remaining_time":5.093187709},
{"learn":[7.921220278],"iteration":30,"passed_time":0.1582368493,"remaining_time":4.946177645},
{"learn":[7.809589039],"iteration":31,"passed_time":0.1590113827,"remaining_time":4.810094326},
{"learn":[7.699675801],"iteration":32,"passed_time":0.1598527771,"remaining_time":4.684170772},
{"learn":[7.60645267],"iteration":33,"passed_time":0.1605342103,"remaining_time":4.56106021},
{"learn":[7.498880302],"iteration":34,"passed_time":0.1613700463,"remaining_time":4.449202705},
{"learn":[7.401158744],"iteration":35,"passed_time":0.162168214,"remaining_time":4.342504396},
{"learn":[7.306431077],"iteration":36,"passed_time":0.1628827282,"remaining_time":4.23935317},
{"learn":[7.223863468],"iteration":37,"passed_time":0.1635645514,"remaining_time":4.140765747},
{"learn":[7.143477682],"iteration":38,"passed_time":0.1641728147,"remaining_time":4.045386537},
{"learn":[7.062817131],"iteration":39,"passed_time":0.1647787746,"remaining_time":3.954690591},
{"learn":[6.990793435],"iteration":40,"passed_time":0.1654931203,"remaining_time":3.870924449},
{"learn":[6.931862224],"iteration":41,"passed_time":0.1661473325,"remaining_time":3.789741536},
{"learn":[6.858296558],"iteration":42,"passed_time":0.1667939554,"remaining_time":3.712135239},
{"learn":[6.786268161],"iteration":43,"passed_time":0.1676361452,"remaining_time":3.642276245},
{"learn":[6.717118549],"iteration":44,"passed_time":0.1684133345,"remaining_time":3.57410521},
{"learn":[6.652948106],"iteration":45,"passed_time":0.1690900963,"remaining_time":3.506781563},
{"learn":[6.589686076],"iteration":46,"passed_time":0.1697635307,"remaining_time":3.442226483},
{"learn":[6.531283097],"iteration":47,"passed_time":0.1703867734,"remaining_time":3.379337673},
{"learn":[6.471368031],"iteration":48,"passed_time":0.1711054098,"remaining_time":3.320841728},
{"learn":[6.416481395],"iteration":49,"passed_time":0.1718296929,"remaining_time":3.264764165},
{"learn":[6.369870822],"iteration":50,"passed_time":0.1725227583,"remaining_time":3.210276424},
{"learn":[6.325678067],"iteration":51,"passed_time":0.1731707732,"remaining_time":3.157036404},
{"learn":[6.275766122],"iteration":52,"passed_time":0.1740939045,"remaining_time":3.110696746},
{"learn":[6.224773967],"iteration":53,"passed_time":0.1747386301,"remaining_time":3.061161927},
{"learn":[6.182249254],"iteration":54,"passed_time":0.1753490303,"remaining_time":3.012815156},
{"learn":[6.139904173],"iteration":55,"passed_time":0.1759424006,"remaining_time":2.965886182},
{"learn":[6.100525536],"iteration":56,"passed_time":0.176533591,"remaining_time":2.920546952},
{"learn":[6.062568564],"iteration":57,"passed_time":0.1771225264,"remaining_time":2.876714136},
{"learn":[6.030559288],"iteration":58,"passed_time":0.1776932179,"remaining_time":2.834056237},
{"learn":[5.997931376],"iteration":59,"passed_time":0.1782949843,"remaining_time":2.793288088},
{"learn":[5.964103835],"iteration":60,"passed_time":0.1788688309,"remaining_time":2.753407085},
{"learn":[5.933729724],"iteration":61,"passed_time":0.1795645954,"remaining_time":2.716638557},
{"learn":[5.901932711],"iteration":62,"passed_time":0.1804822693,"remaining_time":2.684315656},
{"learn":[5.873727795],"iteration":63,"passed_time":0.1810721937,"remaining_time":2.648180833},
{"learn":[5.846485734],"iteration":64,"passed_time":0.1816849838,"remaining_time":2.613468613},
{"learn":[5.820630862],"iteration":65,"passed_time":0.182306855,"remaining_time":2.57991822},
{"learn":[5.793646238],"iteration":66,"passed_time":0.1829029068,"remaining_time":2.546991224},
{"learn":[5.765388646],"iteration":67,"passed_time":0.1834924501,"remaining_time":2.514925934},
{"learn":[5.747073912],"iteration":68,"passed_time":0.184082903,"remaining_time":2.483785256},
{"learn":[5.722315217],"iteration":69,"passed_time":0.1846876001,"remaining_time":2.453706687},
{"learn":[5.699970599],"iteration":70,"passed_time":0.1852890225,"remaining_time":2.42441552},
{"learn":[5.682732647],"iteration":71,"passed_time":0.1860892768,"remaining_time":2.398484012},
{"learn":[5.663525791],"iteration":72,"passed_time":0.1869995104,"remaining_time":2.374637618},
{"learn":[5.642381613],"iteration":73,"passed_time":0.1878076197,"remaining_time":2.350133187},
{"learn":[5.621404779],"iteration":74,"passed_time":0.1884219649,"remaining_time":2.3238709},
{"learn":[5.602460129],"iteration":75,"passed_time":0.1890456146,"remaining_time":2.298396682},
{"learn":[5.587337574],"iteration":76,"passed_time":0.1896878261,"remaining_time":2.273790435},
{"learn":[5.572393026],"iteration":77,"passed_time":0.1902638677,"remaining_time":2.249016488},
{"learn":[5.558425806],"iteration":78,"passed_time":0.1908336319,"remaining_time":2.224781962},
{"learn":[5.541518902],"iteration":79,"passed_time":0.1914877854,"remaining_time":2.202109532},
{"learn":[5.526157283],"iteration":80,"passed_time":0.1923903557,"remaining_time":2.18279922},
{"learn":[5.511746977],"iteration":81,"passed_time":0.1931067094,"remaining_time":2.161853161},
{"learn":[5.504975022],"iteration":82,"passed_time":0.1934996869,"remaining_time":2.137821842},
{"learn":[5.493980522],"iteration":83,"passed_time":0.1941173322,"remaining_time":2.116803289},
{"learn":[5.480745463],"iteration":84,"passed_time":0.1947289752,"remaining_time":2.096200144},
{"learn":[5.464052013],"iteration":85,"passed_time":0.1953344367,"remaining_time":2.075996223},
{"learn":[5.449143727],"iteration":86,"passed_time":0.1959416463,"remaining_time":2.056261185},
{"learn":[5.438255432],"iteration":87,"passed_time":0.1965445483,"remaining_time":2.036916228},
{"learn":[5.425927931],"iteration":88,"passed_time":0.1971751041,"remaining_time":2.018275504},
{"learn":[5.412331217],"iteration":89,"passed_time":0.1977650463,"remaining_time":1.999624357},
{"learn":[5.400691499],"iteration":90,"passed_time":0.1987687302,"remaining_time":1.985503031},
{"learn":[5.391618744],"iteration":91,"passed_time":0.1993957186,"remaining_time":1.967949049},
{"learn":[5.380766572],"iteration":92,"passed_time":0.2000883254,"remaining_time":1.951399044},
{"learn":[5.372207183],"iteration":93,"passed_time":0.2007230206,"remaining_time":1.934628263},
{"learn":[5.362918837],"iteration":94,"passed_time":0.2012986152,"remaining_time":1.917634176},
{"learn":[5.348292324],"iteration":95,"passed_time":0.2019064971,"remaining_time":1.901286181},
{"learn":[5.339772295],"iteration":96,"passed_time":0.2025252861,"remaining_time":1.885364261},
{"learn":[5.331515983],"iteration":97,"passed_time":0.2031099857,"remaining_time":1.869440889},
{"learn":[5.323861644],"iteration":98,"passed_time":0.2037058786,"remaining_time":1.853929258},
{"learn":[5.313277281],"iteration":99,"passed_time":0.2045226347,"remaining_time":1.840703712},
{"learn":[5.30685627],"iteration":100,"passed_time":0.2054577415,"remaining_time":1.828777323},
{"learn":[5.29652059],"iteration":101,"passed_time":0.2061551623,"remaining_time":1.81497388},
{"learn":[5.288350766],"iteration":102,"passed_time":0.2068536191,"remaining_time":1.801433945},
{"learn":[5.27993346],"iteration":103,"passed_time":0.2074654233,"remaining_time":1.787394416},
{"learn":[5.271789139],"iteration":104,"passed_time":0.2080984692,"remaining_time":1.773791714},
{"learn":[5.262684686],"iteration":105,"passed_time":0.2087186919,"remaining_time":1.760325571},
{"learn":[5.251619772],"iteration":106,"passed_time":0.209338258,"remaining_time":1.74709406},
{"learn":[5.241012171],"iteration":107,"passed_time":0.2099570166,"remaining_time":1.734089433},
{"learn":[5.232684032],"iteration":108,"passed_time":0.2108248734,"remaining_time":1.723348277},
{"learn":[5.224267141],"iteration":109,"passed_time":0.2115694089,"remaining_time":1.711788854},
{"learn":[5.216324968],"iteration":110,"passed_time":0.2122788477,"remaining_time":1.700143203},
{"learn":[5.211102527],"iteration":111,"passed_time":0.2129526878,"remaining_time":1.688410596},
{"learn":[5.206364257],"iteration":112,"passed_time":0.2135827105,"remaining_time":1.676529772},
{"learn":[5.196937641],"iteration":113,"passed_time":0.2143507284,"remaining_time":1.665918819},
{"learn":[5.190746047],"iteration":114,"passed_time":0.2149896233,"remaining_time":1.654485362},
{"learn":[5.181885213],"iteration":115,"passed_time":0.215585294,"remaining_time":1.64290862},
{"learn":[5.178293568],"iteration":116,"passed_time":0.2160789354,"remaining_time":1.630749572},
{"learn":[5.170991438],"iteration":117,"passed_time":0.2169934083,"remaining_time":1.62193378},
{"learn":[5.166257212],"iteration":118,"passed_time":0.2178303505,"remaining_time":1.612676796},
{"learn":[5.161421246],"iteration":119,"passed_time":0.2185572283,"remaining_time":1.602753007},
{"learn":[5.158223542],"iteration":120,"passed_time":0.2193385532,"remaining_time":1.593376762},
{"learn":[5.15470988],"iteration":121,"passed_time":0.2198565328,"remaining_time":1.582246195},
{"learn":[5.146388143],"iteration":122,"passed_time":0.2205108136,"remaining_time":1.572260029},
{"learn":[5.139529364],"iteration":123,"passed_time":0.221150105,"remaining_time":1.562318483},
{"learn":[5.134276023],"iteration":124,"passed_time":0.2217529765,"remaining_time":1.552270835},
{"learn":[5.128536065],"iteration":125,"passed_time":0.2223681572,"remaining_time":1.542458487},
{"learn":[5.123300353],"iteration":126,"passed_time":0.2234884317,"remaining_time":1.536262999},
{"learn":[5.116200518],"iteration":127,"passed_time":0.2242607526,"remaining_time":1.527776377},
{"learn":[5.108728704],"iteration":128,"passed_time":0.2249412832,"remaining_time":1.518789594},
{"learn":[5.104075866],"iteration":129,"passed_time":0.2255629052,"remaining_time":1.509536366},
{"learn":[5.100317606],"iteration":130,"passed_time":0.226139464,"remaining_time":1.500115987},
{"learn":[5.095814182],"iteration":131,"passed_time":0.2267370255,"remaining_time":1.490967713},
{"learn":[5.092146915],"iteration":132,"passed_time":0.2274039001,"remaining_time":1.48239986},
{"learn":[5.085258329],"iteration":133,"passed_time":0.2280578634,"remaining_time":1.473866491},
{"learn":[5.079219421],"iteration":134,"passed_time":0.2290242138,"remaining_time":1.467451444},
{"learn":[5.076476829],"iteration":135,"passed_time":0.2300535404,"remaining_time":1.46151661},
{"learn":[5.072133867],"iteration":136,"passed_time":0.2307347344,"remaining_time":1.453460407},
{"learn":[5.067031564],"iteration":137,"passed_time":0.2313761734,"remaining_time":1.445262764},
{"learn":[5.061358312],"iteration":138,"passed_time":0.2320264282,"remaining_time":1.437228451},
{"learn":[5.056759124],"iteration":139,"passed_time":0.2327114673,"remaining_time":1.429513299},
{"learn":[5.050254],"iteration":140,"passed_time":0.233412164,"remaining_time":1.421993254},
{"learn":[5.048376474],"iteration":141,"passed_time":0.2338439789,"remaining_time":1.412944605},
{"learn":[5.042603751],"iteration":142,"passed_time":0.2344418134,"remaining_time":1.405011427},
{"learn":[5.037477349],"iteration":143,"passed_time":0.2352706639,"remaining_time":1.398553391},
{"learn":[5.03230489],"iteration":144,"passed_time":0.2361230738,"remaining_time":1.392311918},
{"learn":[5.025976187],"iteration":145,"passed_time":0.2368765034,"remaining_time":1.385565301},
{"learn":[5.01952451],"iteration":146,"passed_time":0.2375320285,"remaining_time":1.378332111},
{"learn":[5.017569424],"iteration":147,"passed_time":0.2381044171,"remaining_time":1.370709212},
{"learn":[5.008962367],"iteration":148,"passed_time":0.2387041154,"remaining_time":1.363336927},
{"learn":[5.003880266],"iteration":149,"passed_time":0.239314281,"remaining_time":1.356114259},
{"learn":[4.996387564],"iteration":150,"passed_time":0.2399020972,"remaining_time":1.348853513},
{"learn":[4.993361683],"iteration":151,"passed_time":0.24048982,"remaining_time":1.341680048},
{"learn":[4.99005752],"iteration":152,"passed_time":0.2412238963,"remaining_time":1.335402877},
{"learn":[4.986908764],"iteration":153,"passed_time":0.2420431051,"remaining_time":1.32966537},
{"learn":[4.985207175],"iteration":154,"passed_time":0.2427597478,"remaining_time":1.323432173},
{"learn":[4.979003494],"iteration":155,"passed_time":0.2434253846,"remaining_time":1.316993747},
{"learn":[4.973142217],"iteration":156,"passed_time":0.2440554729,"remaining_time":1.310437985},
{"learn":[4.967056696],"iteration":157,"passed_time":0.2447894825,"remaining_time":1.30451104},
{"learn":[4.961460696],"iteration":158,"passed_time":0.2454266162,"remaining_time":1.298137008},
{"learn":[4.954240363],"iteration":159,"passed_time":0.2460130831,"remaining_time":1.291568686},
{"learn":[4.952320707],"iteration":160,"passed_time":0.2464287866,"remaining_time":1.284184795},
{"learn":[4.948337777],"iteration":161,"passed_time":0.247094148,"remaining_time":1.278178371},
{"learn":[4.943228639],"iteration":162,"passed_time":0.2479807557,"remaining_time":1.273373574},
{"learn":[4.938545759],"iteration":163,"passed_time":0.2487908367,"remaining_time":1.26822646},
{"learn":[4.935330572],"iteration":164,"passed_time":0.249487689,"remaining_time":1.262558911},
{"learn":[4.932051543],"iteration":165,"passed_time":0.2501573758,"remaining_time":1.256814768},
{"learn":[4.928964153],"iteration":166,"passed_time":0.2508725145,"remaining_time":1.251358111},
{"learn":[4.922860227],"iteration":167,"passed_time":0.2514684807,"remaining_time":1.245367714},
{"learn":[4.917668772],"iteration":168,"passed_time":0.2520600645,"remaining_time":1.239419607},
{"learn":[4.910365386],"iteration":169,"passed_time":0.2526511275,"remaining_time":1.233531975},
{"learn":[4.906457206],"iteration":170,"passed_time":0.2532892151,"remaining_time":1.227934265},
{"learn":[4.901996508],"iteration":171,"passed_time":0.2543836814,"remaining_time":1.224591211},
{"learn":[4.896816173],"iteration":172,"passed_time":0.2551690987,"remaining_time":1.21979679},
{"learn":[4.891123132],"iteration":173,"passed_time":0.2560445104,"remaining_time":1.215475664},
{"learn":[4.887630202],"iteration":174,"passed_time":0.2566727288,"remaining_time":1.210028579},
{"learn":[4.885259712],"iteration":175,"passed_time":0.2572955334,"remaining_time":1.204610906},
{"learn":[4.880659728],"iteration":176,"passed_time":0.2579056296,"remaining_time":1.199188323},
{"learn":[4.877299723],"iteration":177,"passed_time":0.258508301,"remaining_time":1.193785525},
{"learn":[4.874038772],"iteration":178,"passed_time":0.2591313551,"remaining_time":1.188529847},
{"learn":[4.86943698],"iteration":179,"passed_time":0.2600761525,"remaining_time":1.184791361},
{"learn":[4.861268711],"iteration":180,"passed_time":0.2608804849,"remaining_time":1.180448161},
{"learn":[4.858673056],"iteration":181,"passed_time":0.2615690791,"remaining_time":1.175623663},
{"learn":[4.854036207],"iteration":182,"passed_time":0.2622237375,"remaining_time":1.170692861},
{"learn":[4.85130244],"iteration":183,"passed_time":0.2629830766,"remaining_time":1.166272775},
{"learn":[4.847510084],"iteration":184,"passed_time":0.2635838024,"remaining_time":1.161193508},
{"learn":[4.845691673],"iteration":185,"passed_time":0.2641812397,"remaining_time":1.156148006},
{"learn":[4.842058646],"iteration":186,"passed_time":0.2647841772,"remaining_time":1.15117399},
{"learn":[4.838623675],"iteration":187,"passed_time":0.2654552444,"remaining_time":1.146540737},
{"learn":[4.834602161],"iteration":188,"passed_time":0.2665441805,"remaining_time":1.143742489},
{"learn":[4.830858976],"iteration":189,"passed_time":0.2672347137,"remaining_time":1.139263779},
{"learn":[4.827590511],"iteration":190,"passed_time":0.2679185035,"remaining_time":1.134796175},
{"learn":[4.822246226],"iteration":191,"passed_time":0.2686023917,"remaining_time":1.130368399},
{"learn":[4.816686395],"iteration":192,"passed_time":0.2692486212,"remaining_time":1.125821955},
{"learn":[4.814797121],"iteration":193,"passed_time":0.2698653216,"remaining_time":1.121193037},
{"learn":[4.811639392],"iteration":194,"passed_time":0.2704649319,"remaining_time":1.116534719},
{"learn":[4.804813432],"iteration":195,"passed_time":0.271050494,"remaining_time":1.11186019},
{"learn":[4.80251613],"iteration":196,"passed_time":0.2718567939,"remaining_time":1.108126932},
{"learn":[4.800087884],"iteration":197,"passed_time":0.272646459,"remaining_time":1.104355859},
{"learn":[4.794773135],"iteration":198,"passed_time":0.2734450934,"remaining_time":1.100650853},
{"learn":[4.791664833],"iteration":199,"passed_time":0.2740707171,"remaining_time":1.096282869},
{"learn":[4.785989873],"iteration":200,"passed_time":0.2747511949,"remaining_time":1.092170173},
{"learn":[4.782387142],"iteration":201,"passed_time":0.275427021,"remaining_time":1.088073083},
{"learn":[4.778623704],"iteration":202,"passed_time":0.2760291315,"remaining_time":1.083720285},
{"learn":[4.775772178],"iteration":203,"passed_time":0.276638886,"remaining_time":1.079434085},
{"learn":[4.77023101],"iteration":204,"passed_time":0.2772498926,"remaining_time":1.075188608},
{"learn":[4.764496689],"iteration":205,"passed_time":0.2781768373,"remaining_time":1.072196159},
{"learn":[4.763138716],"iteration":206,"passed_time":0.2790226258,"remaining_time":1.068912765},
{"learn":[4.758053283],"iteration":207,"passed_time":0.2798207823,"remaining_time":1.06547144},
{"learn":[4.755063788],"iteration":208,"passed_time":0.2804560005,"remaining_time":1.061438739},
{"learn":[4.752465267],"iteration":209,"passed_time":0.2811176013,"remaining_time":1.057537643},
{"learn":[4.748067377],"iteration":210,"passed_time":0.2818110975,"remaining_time":1.053786521},
{"learn":[4.744163298],"iteration":211,"passed_time":0.2824798138,"remaining_time":1.049972138},
{"learn":[4.736670896],"iteration":212,"passed_time":0.2830897828,"remaining_time":1.04597023},
{"learn":[4.73349255],"iteration":213,"passed_time":0.2839283863,"remaining_time":1.042839774},
{"learn":[4.731864595],"iteration":214,"passed_time":0.2847052547,"remaining_time":1.039505232},
{"learn":[4.728398311],"iteration":215,"passed_time":0.2854673589,"remaining_time":1.036140784},
{"learn":[4.723865975],"iteration":216,"passed_time":0.2861387297,"remaining_time":1.032472928},
{"learn":[4.723483365],"iteration":217,"passed_time":0.2867911614,"remaining_time":1.028764625},
{"learn":[4.72095416],"iteration":218,"passed_time":0.2874965108,"remaining_time":1.025272945},
{"learn":[4.716173382],"iteration":219,"passed_time":0.28809298,"remaining_time":1.021420565},
{"learn":[4.710563974],"iteration":220,"passed_time":0.2886984408,"remaining_time":1.017629346},
{"learn":[4.707160263],"iteration":221,"passed_time":0.2893184806,"remaining_time":1.013917919},
{"learn":[4.70408351],"iteration":222,"passed_time":0.2902293637,"remaining_time":1.011247603},
{"learn":[4.702501831],"iteration":223,"passed_time":0.2910208034,"remaining_time":1.008179212},
{"learn":[4.700269738],"iteration":224,"passed_time":0.2917403358,"remaining_time":1.004883379},
{"learn":[4.695346302],"iteration":225,"passed_time":0.2924055799,"remaining_time":1.00142442},
{"learn":[4.689769299],"iteration":226,"passed_time":0.2932221814,"remaining_time":0.99850549},
{"learn":[4.687919514],"iteration":227,"passed_time":0.2938547205,"remaining_time":0.994981773},
{"learn":[4.682982074],"iteration":228,"passed_time":0.2944608143,"remaining_time":0.9913942699},
{"learn":[4.679578702],"iteration":229,"passed_time":0.2950388103,"remaining_time":0.9877386257},
{"learn":[4.675751423],"iteration":230,"passed_time":0.2958648994,"remaining_time":0.984935531},
{"learn":[4.672710726],"iteration":231,"passed_time":0.2966767624,"remaining_time":0.982102386},
{"learn":[4.6690533],"iteration":232,"passed_time":0.2975496373,"remaining_time":0.9794874328},
{"learn":[4.667595702],"iteration":233,"passed_time":0.2982837665,"remaining_time":0.9764331843},
{"learn":[4.664241291],"iteration":234,"passed_time":0.2989233425,"remaining_time":0.9730908808},
{"learn":[4.662246999],"iteration":235,"passed_time":0.2996461939,"remaining_time":0.9700410683},
{"learn":[4.658668443],"iteration":236,"passed_time":0.3002474882,"remaining_time":0.9666195507},
{"learn":[4.658017572],"iteration":237,"passed_time":0.3008244706,"remaining_time":0.9631438932},
{"learn":[4.657656705],"iteration":238,"passed_time":0.3014002171,"remaining_time":0.9596885574},
{"learn":[4.653242871],"iteration":239,"passed_time":0.3022174496,"remaining_time":0.9570219237},
{"learn":[4.6507302],"iteration":240,"passed_time":0.3030018929,"remaining_time":0.9542673724},
{"learn":[4.647671336],"iteration":241,"passed_time":0.3037365146,"remaining_time":0.95137305},
{"learn":[4.645506007],"iteration":242,"passed_time":0.3044345503,"remaining_time":0.948382529},
{"learn":[4.641297906],"iteration":243,"passed_time":0.3050600556,"remaining_time":0.9451860739},
{"learn":[4.63798107],"iteration":244,"passed_time":0.3058370312,"remaining_time":0.9424773819},
{"learn":[4.635062318],"iteration":245,"passed_time":0.3065700526,"remaining_time":0.9396496734},
{"learn":[4.631606017],"iteration":246,"passed_time":0.3072006157,"remaining_time":0.9365265735},
{"learn":[4.630215494],"iteration":247,"passed_time":0.3079662315,"remaining_time":0.933833089},
{"learn":[4.62729814],"iteration":248,"passed_time":0.3088563661,"remaining_time":0.9315306463},
{"learn":[4.624691756],"iteration":249,"passed_time":0.3096075227,"remaining_time":0.9288225682},
{"learn":[4.621840053],"iteration":250,"passed_time":0.3102776916,"remaining_time":0.9258884105},
{"learn":[4.619602091],"iteration":251,"passed_time":0.3109942714,"remaining_time":0.9231099802},
{"learn":[4.613584029],"iteration":252,"passed_time":0.3117281328,"remaining_time":0.9203988744},
{"learn":[4.6119388],"iteration":253,"passed_time":0.3123780227,"remaining_time":0.9174567124},
{"learn":[4.60870702],"iteration":254,"passed_time":0.313012969,"remaining_time":0.9144888703},
{"learn":[4.604771557],"iteration":255,"passed_time":0.3135948661,"remaining_time":0.9113850796},
{"learn":[4.604231277],"iteration":256,"passed_time":0.3146575589,"remaining_time":0.9096909193},
{"learn":[4.600750354],"iteration":257,"passed_time":0.3153938854,"remaining_time":0.9070630348},
{"learn":[4.596488253],"iteration":258,"passed_time":0.3161288349,"remaining_time":0.9044458174},
{"learn":[4.59470784],"iteration":259,"passed_time":0.3168361041,"remaining_time":0.9017642962},
{"learn":[4.588818005],"iteration":260,"passed_time":0.3174478797,"remaining_time":0.8988275214},
{"learn":[4.585054174],"iteration":261,"passed_time":0.3181369742,"remaining_time":0.8961262861},
{"learn":[4.581471435],"iteration":262,"passed_time":0.3187283905,"remaining_time":0.8931666306},
{"learn":[4.577555199],"iteration":263,"passed_time":0.3193281267,"remaining_time":0.8902481107},
{"learn":[4.57457145],"iteration":264,"passed_time":0.3199263469,"remaining_time":0.8873428867},
{"learn":[4.573029224],"iteration":265,"passed_time":0.3208952383,"remaining_time":0.8854778381},
{"learn":[4.571326203],"iteration":266,"passed_time":0.3216517382,"remaining_time":0.8830364199},
{"learn":[4.571019224],"iteration":267,"passed_time":0.3223462106,"remaining_time":0.8804381574},
{"learn":[4.565766631],"iteration":268,"passed_time":0.3230974587,"remaining_time":0.8780083358},
{"learn":[4.563383471],"iteration":269,"passed_time":0.3237765464,"remaining_time":0.8753958476},
{"learn":[4.558165805],"iteration":270,"passed_time":0.3244512138,"remaining_time":0.8727857375},
{"learn":[4.55629209],"iteration":271,"passed_time":0.3251422149,"remaining_time":0.8702335751},
{"learn":[4.549383848],"iteration":272,"passed_time":0.3258629649,"remaining_time":0.8677742692},
{"learn":[4.546227503],"iteration":273,"passed_time":0.3269156536,"remaining_time":0.8662071697},
{"learn":[4.540620977],"iteration":274,"passed_time":0.3278204201,"remaining_time":0.8642538347},
{"learn":[4.532898237],"iteration":275,"passed_time":0.3285593848,"remaining_time":0.8618731689},
{"learn":[4.529757367],"iteration":276,"passed_time":0.3292170768,"remaining_time":0.8592922258},
{"learn":[4.52579294],"iteration":277,"passed_time":0.3299039157,"remaining_time":0.856800817},
{"learn":[4.521572155],"iteration":278,"passed_time":0.3305124328,"remaining_time":0.8541199429},
{"learn":[4.518818099],"iteration":279,"passed_time":0.3311015064,"remaining_time":0.8514038736},
{"learn":[4.514012334],"iteration":280,"passed_time":0.3317504864,"remaining_time":0.8488562267},
{"learn":[4.508331416],"iteration":281,"passed_time":0.3326195728,"remaining_time":0.8468824585},
{"learn":[4.506038537],"iteration":282,"passed_time":0.3333368773,"remaining_time":0.8445319472},
{"learn":[4.505805643],"iteration":283,"passed_time":0.3340742854,"remaining_time":0.8422436209},
{"learn":[4.501550352],"iteration":284,"passed_time":0.3347682402,"remaining_time":0.839857164},
{"learn":[4.494692643],"iteration":285,"passed_time":0.335435588,"remaining_time":0.8374161184},
{"learn":[4.489330245],"iteration":286,"passed_time":0.3361006533,"remaining_time":0.8349817623},
{"learn":[4.484826955],"iteration":287,"passed_time":0.336708311,"remaining_time":0.832417769},
{"learn":[4.478285428],"iteration":288,"passed_time":0.3373032119,"remaining_time":0.8298359296},
{"learn":[4.475311671],"iteration":289,"passed_time":0.3379465964,"remaining_time":0.8273864946},
{"learn":[4.471581298],"iteration":290,"passed_time":0.338776506,"remaining_time":0.825403927},
{"learn":[4.469164956],"iteration":291,"passed_time":0.3396927681,"remaining_time":0.8236386296},
{"learn":[4.462068024],"iteration":292,"passed_time":0.3406023907,"remaining_time":0.8218631066},
{"learn":[4.458540976],"iteration":293,"passed_time":0.3412172952,"remaining_time":0.8193857497},
{"learn":[4.455757458],"iteration":294,"passed_time":0.3418498656,"remaining_time":0.8169632381},
{"learn":[4.453027414],"iteration":295,"passed_time":0.3424783447,"remaining_time":0.8145430902},
{"learn":[4.450659338],"iteration":296,"passed_time":0.3431116576,"remaining_time":0.8121464488},
{"learn":[4.444696901],"iteration":297,"passed_time":0.3437127599,"remaining_time":0.8096857632},
{"learn":[4.442052813],"iteration":298,"passed_time":0.3444137373,"remaining_time":0.8074716717},
{"learn":[4.440036756],"iteration":299,"passed_time":0.3451709372,"remaining_time":0.8053988536},
{"learn":[4.435017051],"iteration":300,"passed_time":0.3459776364,"remaining_time":0.803449727},
{"learn":[4.429962125],"iteration":301,"passed_time":0.3466463473,"remaining_time":0.8011892398},
{"learn":[4.427666256],"iteration":302,"passed_time":0.3473154177,"remaining_time":0.7989400863},
{"learn":[4.425030004],"iteration":303,"passed_time":0.3480011222,"remaining_time":0.7967394115},
{"learn":[4.422588771],"iteration":304,"passed_time":0.3485949747,"remaining_time":0.7943393687},
{"learn":[4.418936667],"iteration":305,"passed_time":0.3491969942,"remaining_time":0.7919696536},
{"learn":[4.416887976],"iteration":306,"passed_time":0.349782949,"remaining_time":0.789575191},
{"learn":[4.413773354],"iteration":307,"passed_time":0.3505257415,"remaining_time":0.7875448478},
{"learn":[4.411129391],"iteration":308,"passed_time":0.351485946,"remaining_time":0.7860090248},
{"learn":[4.40850819],"iteration":309,"passed_time":0.3522185211,"remaining_time":0.7839702566},
{"learn":[4.404880292],"iteration":310,"passed_time":0.3528450231,"remaining_time":0.7817048904},
{"learn":[4.404593827],"iteration":311,"passed_time":0.353443187,"remaining_time":0.7793875406},
{"learn":[4.402139942],"iteration":312,"passed_time":0.3541220298,"remaining_time":0.777258257},
{"learn":[4.400284725],"iteration":313,"passed_time":0.3547095026,"remaining_time":0.7749385949},
{"learn":[4.395805521],"iteration":314,"passed_time":0.3553190782,"remaining_time":0.7726779954},
{"learn":[4.392838833],"iteration":315,"passed_time":0.3559207212,"remaining_time":0.7704106751},
{"learn":[4.389213061],"iteration":316,"passed_time":0.3566882219,"remaining_time":0.7685112163},
{"learn":[4.3861981],"iteration":317,"passed_time":0.3575059886,"remaining_time":0.76672668},
{"learn":[4.385054234],"iteration":318,"passed_time":0.3582145526,"remaining_time":0.7647150793},
{"learn":[4.379364607],"iteration":319,"passed_time":0.3588831829,"remaining_time":0.7626267636},
{"learn":[4.378387619],"iteration":320,"passed_time":0.3595262002,"remaining_time":0.760493115},
{"learn":[4.375816727],"iteration":321,"passed_time":0.3602616091,"remaining_time":0.7585632639},
{"learn":[4.374600202],"iteration":322,"passed_time":0.3609195637,"remaining_time":0.7564784664},
{"learn":[4.37098897],"iteration":323,"passed_time":0.3615280562,"remaining_time":0.7542992778},
{"learn":[4.367418484],"iteration":324,"passed_time":0.3621246519,"remaining_time":0.7521050462},
{"learn":[4.363584638],"iteration":325,"passed_time":0.3629433547,"remaining_time":0.7503798192},
{"learn":[4.360770706],"iteration":326,"passed_time":0.3637874619,"remaining_time":0.7487124215},
{"learn":[4.358675808],"iteration":327,"passed_time":0.3646562417,"remaining_time":0.7471005927},
{"learn":[4.354228195],"iteration":328,"passed_time":0.3653428156,"remaining_time":0.7451216694},
{"learn":[4.353773425],"iteration":329,"passed_time":0.3660429849,"remaining_time":0.7431781815},
{"learn":[4.351648009],"iteration":330,"passed_time":0.3666660001,"remaining_time":0.7410862661},
{"learn":[4.348209927],"iteration":331,"passed_time":0.3672567878,"remaining_time":0.7389383561},
{"learn":[4.345852733],"iteration":332,"passed_time":0.3678571541,"remaining_time":0.7368189844},
{"learn":[4.34237339],"iteration":333,"passed_time":0.3684734966,"remaining_time":0.734740565},
{"learn":[4.340814362],"iteration":334,"passed_time":0.3693603098,"remaining_time":0.7332077792},
{"learn":[4.339707068],"iteration":335,"passed_time":0.3701219813,"remaining_time":0.7314315344},
{"learn":[4.335430786],"iteration":336,"passed_time":0.3708850294,"remaining_time":0.7296640192},
{"learn":[4.33521887],"iteration":337,"passed_time":0.3715693997,"remaining_time":0.7277483509},
{"learn":[4.328507238],"iteration":338,"passed_time":0.3722997782,"remaining_time":0.725929656},
{"learn":[4.326140732],"iteration":339,"passed_time":0.3728955075,"remaining_time":0.7238559852},
{"learn":[4.323785636],"iteration":340,"passed_time":0.3734687817,"remaining_time":0.7217475869},
{"learn":[4.320632534],"iteration":341,"passed_time":0.374061079,"remaining_time":0.719684766},
{"learn":[4.31973724],"iteration":342,"passed_time":0.3746368386,"remaining_time":0.7175988425},
{"learn":[4.318000924],"iteration":343,"passed_time":0.3754927763,"remaining_time":0.716055992},
{"learn":[4.312713628],"iteration":344,"passed_time":0.3762974497,"remaining_time":0.7144197958},
{"learn":[4.308220789],"iteration":345,"passed_time":0.3771517627,"remaining_time":0.7128822336},
{"learn":[4.305890947],"iteration":346,"passed_time":0.3779578478,"remaining_time":0.711257852},
{"learn":[4.305137856],"iteration":347,"passed_time":0.378772314,"remaining_time":0.7096538757},
{"learn":[4.304787172],"iteration":348,"passed_time":0.3793794519,"remaining_time":0.7076676881},
{"learn":[4.30350134],"iteration":349,"passed_time":0.3799773859,"remaining_time":0.7056722882},
{"learn":[4.30293809],"iteration":350,"passed_time":0.3805635289,"remaining_time":0.7036630491},
{"learn":[4.299548459],"iteration":351,"passed_time":0.3814476321,"remaining_time":0.7022104137},
{"learn":[4.294768408],"iteration":352,"passed_time":0.3821439768,"remaining_time":0.700416864},
{"learn":[4.294581479],"iteration":353,"passed_time":0.38286747,"remaining_time":0.6986790555},
{"learn":[4.292551604],"iteration":354,"passed_time":0.3836397362,"remaining_time":0.697035577},
{"learn":[4.288628894],"iteration":355,"passed_time":0.384394029,"remaining_time":0.6953644794},
{"learn":[4.287802767],"iteration":356,"passed_time":0.3850989033,"remaining_time":0.6936095092},
{"learn":[4.284566905],"iteration":357,"passed_time":0.3857729605,"remaining_time":0.6918051415},
{"learn":[4.27890232],"iteration":358,"passed_time":0.3863671432,"remaining_time":0.6898644534},
{"learn":[4.276938023],"iteration":359,"passed_time":0.3871901914,"remaining_time":0.688338118},
{"learn":[4.273425094],"iteration":360,"passed_time":0.3880668154,"remaining_time":0.6869105125},
{"learn":[4.269726505],"iteration":361,"passed_time":0.3887884687,"remaining_time":0.6852128261},
{"learn":[4.265565857],"iteration":362,"passed_time":0.3895477781,"remaining_time":0.6835865969},
{"learn":[4.262117173],"iteration":363,"passed_time":0.3902623109,"remaining_time":0.6818868949},
{"learn":[4.259185148],"iteration":364,"passed_time":0.3909039593,"remaining_time":0.6800657923},
{"learn":[4.257668507],"iteration":365,"passed_time":0.3915046227,"remaining_time":0.6781801387},
{"learn":[4.253432436],"iteration":366,"passed_time":0.392128039,"remaining_time":0.6763407321},
{"learn":[4.250216667],"iteration":367,"passed_time":0.3927324283,"remaining_time":0.6744752573},
{"learn":[4.24514828],"iteration":368,"passed_time":0.3938329322,"remaining_time":0.673464987},
{"learn":[4.244015772],"iteration":369,"passed_time":0.3945670154,"remaining_time":0.6718303235},
{"learn":[4.240329192],"iteration":370,"passed_time":0.3952547279,"remaining_time":0.6701218972},
{"learn":[4.236718014],"iteration":371,"passed_time":0.3959250627,"remaining_time":0.6683896219},
{"learn":[4.233495944],"iteration":372,"passed_time":0.39668378,"remaining_time":0.6668116087},
{"learn":[4.230357491],"iteration":373,"passed_time":0.3972900045,"remaining_time":0.6649827348},
{"learn":[4.227381215],"iteration":374,"passed_time":0.3978847773,"remaining_time":0.6631412955},
{"learn":[4.226169067],"iteration":375,"passed_time":0.3984606203,"remaining_time":0.6612750719},
{"learn":[4.225963861],"iteration":376,"passed_time":0.3991481588,"remaining_time":0.659600273},
{"learn":[4.224346548],"iteration":377,"passed_time":0.4001194891,"remaining_time":0.6583976778},
{"learn":[4.222595381],"iteration":378,"passed_time":0.4008561299,"remaining_time":0.6568117591},
{"learn":[4.219700938],"iteration":379,"passed_time":0.401493063,"remaining_time":0.6550676292},
{"learn":[4.216356207],"iteration":380,"passed_time":0.4021462839,"remaining_time":0.6533557736},
{"learn":[4.214326494],"iteration":381,"passed_time":0.4028116843,"remaining_time":0.6516691646},
{"learn":[4.212901398],"iteration":382,"passed_time":0.403506456,"remaining_time":0.6500352046},
{"learn":[4.211331091],"iteration":383,"passed_time":0.4041742683,"remaining_time":0.6483628887},
{"learn":[4.208624791],"iteration":384,"passed_time":0.4047829119,"remaining_time":0.6466012749},
{"learn":[4.204659106],"iteration":385,"passed_time":0.4058365784,"remaining_time":0.645553521},
{"learn":[4.202968852],"iteration":386,"passed_time":0.4065490808,"remaining_time":0.6439653398},
{"learn":[4.197261935],"iteration":387,"passed_time":0.4073414682,"remaining_time":0.6425076766},
{"learn":[4.196934403],"iteration":388,"passed_time":0.4079768812,"remaining_time":0.6408068752},
{"learn":[4.192479929],"iteration":389,"passed_time":0.4086871408,"remaining_time":0.6392286048},
{"learn":[4.190243116],"iteration":390,"passed_time":0.4094214165,"remaining_time":0.6376921806},
{"learn":[4.185852431],"iteration":391,"passed_time":0.410076012,"remaining_time":0.6360362635},
{"learn":[4.180967944],"iteration":392,"passed_time":0.4106947636,"remaining_time":0.6343300801},
{"learn":[4.178283162],"iteration":393,"passed_time":0.4114296602,"remaining_time":0.6328080561},
{"learn":[4.176341157],"iteration":394,"passed_time":0.4122127258,"remaining_time":0.6313637953},
{"learn":[4.176041504],"iteration":395,"passed_time":0.4129360848,"remaining_time":0.6298318061},
{"learn":[4.175564513],"iteration":396,"passed_time":0.4137049367,"remaining_time":0.6283729894},
{"learn":[4.170830274],"iteration":397,"passed_time":0.4144517861,"remaining_time":0.6268843599},
{"learn":[4.167804808],"iteration":398,"passed_time":0.4150980727,"remaining_time":0.6252479741},
{"learn":[4.165860548],"iteration":399,"passed_time":0.4156915294,"remaining_time":0.6235372941},
{"learn":[4.160950571],"iteration":400,"passed_time":0.4162886288,"remaining_time":0.6218376276},
{"learn":[4.158544115],"iteration":401,"passed_time":0.4168487958,"remaining_time":0.6200885072},
{"learn":[4.154448767],"iteration":402,"passed_time":0.4174963479,"remaining_time":0.6184747386},
{"learn":[4.15197457],"iteration":403,"passed_time":0.4185409335,"remaining_time":0.6174514762},
{"learn":[4.149562679],"iteration":404,"passed_time":0.4195676165,"remaining_time":0.616401807},
{"learn":[4.149327961],"iteration":405,"passed_time":0.4203370739,"remaining_time":0.614975916},
{"learn":[4.147444889],"iteration":406,"passed_time":0.4211451678,"remaining_time":0.6136095442},
{"learn":[4.147254809],"iteration":407,"passed_time":0.4217602837,"remaining_time":0.6119659018},
{"learn":[4.144589165],"iteration":408,"passed_time":0.4224485458,"remaining_time":0.6104329843},
{"learn":[4.141691034],"iteration":409,"passed_time":0.423052431,"remaining_time":0.6087827665},
{"learn":[4.138893468],"iteration":410,"passed_time":0.4242317082,"remaining_time":0.6079622291},
{"learn":[4.136964597],"iteration":411,"passed_time":0.4251569119,"remaining_time":0.6067773403},
{"learn":[4.133773523],"iteration":412,"passed_time":0.425922523,"remaining_time":0.6053668789},
{"learn":[4.131363444],"iteration":413,"passed_time":0.4266365328,"remaining_time":0.6038864932},
{"learn":[4.130228592],"iteration":414,"passed_time":0.427323789,"remaining_time":0.6023720881},
{"learn":[4.12884186],"iteration":415,"passed_time":0.4279420399,"remaining_time":0.6007647868},
{"learn":[4.12413494],"iteration":416,"passed_time":0.4285440347,"remaining_time":0.5991395018},
{"learn":[4.119422508],"iteration":417,"passed_time":0.4291392758,"remaining_time":0.5975097093},
{"learn":[4.117038244],"iteration":418,"passed_time":0.4298506234,"remaining_time":0.5960458524},
{"learn":[4.116067631],"iteration":419,"passed_time":0.4305837821,"remaining_time":0.594615699},
{"learn":[4.110343455],"iteration":420,"passed_time":0.4314119189,"remaining_time":0.5933194799},
{"learn":[4.105604544],"iteration":421,"passed_time":0.4320587463,"remaining_time":0.5917771454},
{"learn":[4.103390131],"iteration":422,"passed_time":0.4327692125,"remaining_time":0.5903258525},
{"learn":[4.096724402],"iteration":423,"passed_time":0.4335767957,"remaining_time":0.5890099866},
{"learn":[4.093431279],"iteration":424,"passed_time":0.434273341,"remaining_time":0.5875462848},
{"learn":[4.091412744],"iteration":425,"passed_time":0.4349176311,"remaining_time":0.5860157753},
{"learn":[4.091192901],"iteration":426,"passed_time":0.4355567288,"remaining_time":0.5844824488},
{"learn":[4.088994581],"iteration":427,"passed_time":0.4365158371,"remaining_time":0.5833809786},
{"learn":[4.087845355],"iteration":428,"passed_time":0.437292287,"remaining_time":0.5820370534},
{"learn":[4.083650279],"iteration":429,"passed_time":0.4380016008,"remaining_time":0.5806067731},
{"learn":[4.079840652],"iteration":430,"passed_time":0.4386675813,"remaining_time":0.5791226305},
{"learn":[4.075707828],"iteration":431,"passed_time":0.4394139509,"remaining_time":0.5777479725},
{"learn":[4.071345409],"iteration":432,"passed_time":0.4400061163,"remaining_time":0.5761742909},
{"learn":[4.067460475],"iteration":433,"passed_time":0.4406074315,"remaining_time":0.574617065},
{"learn":[4.064914749],"iteration":434,"passed_time":0.4411963909,"remaining_time":0.5730481859},
{"learn":[4.063823175],"iteration":435,"passed_time":0.4418942421,"remaining_time":0.5716246619},
{"learn":[4.058898471],"iteration":436,"passed_time":0.4426753225,"remaining_time":0.5703116855},
{"learn":[4.054120355],"iteration":437,"passed_time":0.4433748389,"remaining_time":0.5688964827},
{"learn":[4.052715901],"iteration":438,"passed_time":0.4440491187,"remaining_time":0.5674522906},
{"learn":[4.052114167],"iteration":439,"passed_time":0.4447144238,"remaining_time":0.5660001757},
{"learn":[4.051377267],"iteration":440,"passed_time":0.4454059629,"remaining_time":0.5645848827},
{"learn":[4.049275336],"iteration":441,"passed_time":0.4460002289,"remaining_time":0.5630500627},
{"learn":[4.047099198],"iteration":442,"passed_time":0.4466842313,"remaining_time":0.5616323178},
{"learn":[4.044348685],"iteration":443,"passed_time":0.4474176653,"remaining_time":0.5602797791},
{"learn":[4.042822379],"iteration":444,"passed_time":0.4485746648,"remaining_time":0.5594582898},
{"learn":[4.041258611],"iteration":445,"passed_time":0.4494153156,"remaining_time":0.5582423427},
{"learn":[4.040044254],"iteration":446,"passed_time":0.4502824623,"remaining_time":0.5570608539},
{"learn":[4.036860137],"iteration":447,"passed_time":0.4509477243,"remaining_time":0.5556320174},
{"learn":[4.036372284],"iteration":448,"passed_time":0.451533922,"remaining_time":0.5541095568},
{"learn":[4.03368231],"iteration":449,"passed_time":0.45212838,"remaining_time":0.5526013534},
{"learn":[4.032439519],"iteration":450,"passed_time":0.4527276363,"remaining_time":0.5511030429},
{"learn":[4.032008634],"iteration":451,"passed_time":0.4533151254,"remaining_time":0.549594444},
{"learn":[4.030034932],"iteration":452,"passed_time":0.4540693164,"remaining_time":0.5482912054},
{"learn":[4.028173412],"iteration":453,"passed_time":0.4548198262,"remaining_time":0.5469859584},
{"learn":[4.023806097],"iteration":454,"passed_time":0.4556112891,"remaining_time":0.5457322034},
{"learn":[4.020239186],"iteration":455,"passed_time":0.4563368049,"remaining_time":0.5444018024},
{"learn":[4.017384838],"iteration":456,"passed_time":0.45711682,"remaining_time":0.5431388036},
{"learn":[4.016468229],"iteration":457,"passed_time":0.4578667304,"remaining_time":0.5418422879},
{"learn":[4.014530169],"iteration":458,"passed_time":0.4584965618,"remaining_time":0.540406623},
{"learn":[4.012884822],"iteration":459,"passed_time":0.4590909543,"remaining_time":0.5389328594},
{"learn":[4.008924707],"iteration":460,"passed_time":0.4596857626,"remaining_time":0.5374633971},
{"learn":[4.008286778],"iteration":461,"passed_time":0.4606914854,"remaining_time":0.5364762319},
{"learn":[4.006444202],"iteration":462,"passed_time":0.4615733585,"remaining_time":0.5353453424},
{"learn":[4.003284363],"iteration":463,"passed_time":0.4622940329,"remaining_time":0.5340293139},
{"learn":[3.999811484],"iteration":464,"passed_time":0.4630082367,"remaining_time":0.5327084014},
{"learn":[3.997483319],"iteration":465,"passed_time":0.463724339,"remaining_time":0.5313922682},
{"learn":[3.99708333],"iteration":466,"passed_time":0.4643142125,"remaining_time":0.5299346365},
{"learn":[3.995860263],"iteration":467,"passed_time":0.4649338766,"remaining_time":0.5285145777},
{"learn":[3.994131111],"iteration":468,"passed_time":0.465554431,"remaining_time":0.52709894},
{"learn":[3.993125499],"iteration":469,"passed_time":0.466784876,"remaining_time":0.5263744347},
{"learn":[3.992954084],"iteration":470,"passed_time":0.4674649091,"remaining_time":0.52502959},
{"learn":[3.990635743],"iteration":471,"passed_time":0.4681266672,"remaining_time":0.5236671192},
{"learn":[3.986678254],"iteration":472,"passed_time":0.468806205,"remaining_time":0.5223274208},
{"learn":[3.986393291],"iteration":473,"passed_time":0.4694518239,"remaining_time":0.5209528679},
{"learn":[3.986152671],"iteration":474,"passed_time":0.4700456077,"remaining_time":0.5195240928},
{"learn":[3.985596662],"iteration":475,"passed_time":0.4705748131,"remaining_time":0.5180277354},
{"learn":[3.983853457],"iteration":476,"passed_time":0.4711523886,"remaining_time":0.516588468},
{"learn":[3.983263928],"iteration":477,"passed_time":0.471738368,"remaining_time":0.5151619835},
{"learn":[3.980067202],"iteration":478,"passed_time":0.4730092878,"remaining_time":0.5144840062},
{"learn":[3.978115407],"iteration":479,"passed_time":0.4739317287,"remaining_time":0.5134260394},
{"learn":[3.972661644],"iteration":480,"passed_time":0.4746929442,"remaining_time":0.5121946737},
{"learn":[3.969938254],"iteration":481,"passed_time":0.4754651845,"remaining_time":0.510977107},
{"learn":[3.968211434],"iteration":482,"passed_time":0.4761627477,"remaining_time":0.5096814504},
{"learn":[3.966113368],"iteration":483,"passed_time":0.4767589214,"remaining_time":0.5082801723},
{"learn":[3.962246044],"iteration":484,"passed_time":0.4773465763,"remaining_time":0.5068731686},
{"learn":[3.961319703],"iteration":485,"passed_time":0.4779276332,"remaining_time":0.5054625586},
{"learn":[3.96078191],"iteration":486,"passed_time":0.4787585303,"remaining_time":0.5043185339},
{"learn":[3.958913633],"iteration":487,"passed_time":0.479484126,"remaining_time":0.5030653125},
{"learn":[3.957428286],"iteration":488,"passed_time":0.4801791577,"remaining_time":0.50178231},
{"learn":[3.952641965],"iteration":489,"passed_time":0.4808749377,"remaining_time":0.5005024862},
{"learn":[3.951486786],"iteration":490,"passed_time":0.4817571332,"remaining_time":0.4994182909},
{"learn":[3.94938344],"iteration":491,"passed_time":0.482386373,"remaining_time":0.4980737347},
{"learn":[3.947297924],"iteration":492,"passed_time":0.4830503852,"remaining_time":0.4967678404},
{"learn":[3.946284886],"iteration":493,"passed_time":0.483714399,"remaining_time":0.4954645463},
{"learn":[3.943288204],"iteration":494,"passed_time":0.4844229861,"remaining_time":0.494209309},
{"learn":[3.943076488],"iteration":495,"passed_time":0.4854645921,"remaining_time":0.4932946662},
{"learn":[3.942347078],"iteration":496,"passed_time":0.4861767833,"remaining_time":0.4920461207},
{"learn":[3.940251541],"iteration":497,"passed_time":0.4870112959,"remaining_time":0.4909230333},
{"learn":[3.939011019],"iteration":498,"passed_time":0.4876584203,"remaining_time":0.489612963},
{"learn":[3.938760512],"iteration":499,"passed_time":0.4882523761,"remaining_time":0.4882523761},
{"learn":[3.934522727],"iteration":500,"passed_time":0.4889601436,"remaining_time":0.4870082069},
{"learn":[3.930091193],"iteration":501,"passed_time":0.4895532278,"remaining_time":0.4856524052},
{"learn":[3.927671752],"iteration":502,"passed_time":0.4901375887,"remaining_time":0.4842910171},
{"learn":[3.927280041],"iteration":503,"passed_time":0.4910491086,"remaining_time":0.4832546783},
{"learn":[3.925987561],"iteration":504,"passed_time":0.491804235,"remaining_time":0.4820655372},
{"learn":[3.921645957],"iteration":505,"passed_time":0.4924684312,"remaining_time":0.4807893379},
{"learn":[3.920333743],"iteration":506,"passed_time":0.4931521346,"remaining_time":0.4795345214},
{"learn":[3.918659461],"iteration":507,"passed_time":0.493841324,"remaining_time":0.4782872665},
{"learn":[3.916124385],"iteration":508,"passed_time":0.4944606688,"remaining_time":0.4769748298},
{"learn":[3.913849268],"iteration":509,"passed_time":0.4950439552,"remaining_time":0.4756304667},
{"learn":[3.912826119],"iteration":510,"passed_time":0.4956330411,"remaining_time":0.4742946322},
{"learn":[3.910034145],"iteration":511,"passed_time":0.4962161068,"remaining_time":0.4729559768},
{"learn":[3.90792379],"iteration":512,"passed_time":0.4971455853,"remaining_time":0.4719491229},
{"learn":[3.907823851],"iteration":513,"passed_time":0.4978950398,"remaining_time":0.4707723528},
{"learn":[3.904527401],"iteration":514,"passed_time":0.498579797,"remaining_time":0.4695363137},
{"learn":[3.903378283],"iteration":515,"passed_time":0.4992608792,"remaining_time":0.4682989642},
{"learn":[3.902170135],"iteration":516,"passed_time":0.499934474,"remaining_time":0.4670567716},
{"learn":[3.899435429],"iteration":517,"passed_time":0.5005565368,"remaining_time":0.4657688239},
{"learn":[3.897497505],"iteration":518,"passed_time":0.5012361167,"remaining_time":0.4645367478},
{"learn":[3.896426119],"iteration":519,"passed_time":0.5018412959,"remaining_time":0.4632381193},
{"learn":[3.896044669],"iteration":520,"passed_time":0.5026094847,"remaining_time":0.4620920214},
{"learn":[3.892795942],"iteration":521,"passed_time":0.5037333058,"remaining_time":0.4612730272},
{"learn":[3.892413888],"iteration":522,"passed_time":0.5044783802,"remaining_time":0.4601074328},
{"learn":[3.891738985],"iteration":523,"passed_time":0.5051039627,"remaining_time":0.4588348974},
{"learn":[3.88822057],"iteration":524,"passed_time":0.5057945854,"remaining_time":0.4576236725},
{"learn":[3.883837053],"iteration":525,"passed_time":0.5063989276,"remaining_time":0.4563366762},
{"learn":[3.881769742],"iteration":526,"passed_time":0.5069938208,"remaining_time":0.4550437898},
{"learn":[3.880356898],"iteration":527,"passed_time":0.5075812011,"remaining_time":0.4537468313},
{"learn":[3.879250273],"iteration":528,"passed_time":0.5081577977,"remaining_time":0.4524429541},
{"learn":[3.877174493],"iteration":529,"passed_time":0.5090138391,"remaining_time":0.4513896309},
{"learn":[3.875854201],"iteration":530,"passed_time":0.5098032222,"remaining_time":0.4502781756},
{"learn":[3.873189396],"iteration":531,"passed_time":0.5104863263,"remaining_time":0.4490744374},
{"learn":[3.871583368],"iteration":532,"passed_time":0.5112128936,"remaining_time":0.4479107341},
{"learn":[3.869622679],"iteration":533,"passed_time":0.5118669981,"remaining_time":0.4466854328},
{"learn":[3.866860164],"iteration":534,"passed_time":0.5125525699,"remaining_time":0.4454896168},
{"learn":[3.864498444],"iteration":535,"passed_time":0.5131742883,"remaining_time":0.4442404287},
{"learn":[3.861416322],"iteration":536,"passed_time":0.513769524,"remaining_time":0.4429707442},
{"learn":[3.860265769],"iteration":537,"passed_time":0.5143158023,"remaining_time":0.4416615254},
{"learn":[3.859328725],"iteration":538,"passed_time":0.5151362524,"remaining_time":0.4405896333},
{"learn":[3.858521278],"iteration":539,"passed_time":0.5159000754,"remaining_time":0.4394704346},
{"learn":[3.85599111],"iteration":540,"passed_time":0.5166199749,"remaining_time":0.4383152837},
{"learn":[3.852379816],"iteration":541,"passed_time":0.5172648166,"remaining_time":0.4370983137},
{"learn":[3.851327537],"iteration":542,"passed_time":0.5179466984,"remaining_time":0.4359146246},
{"learn":[3.847854898],"iteration":543,"passed_time":0.5185813678,"remaining_time":0.4346932053},
{"learn":[3.847083414],"iteration":544,"passed_time":0.519173024,"remaining_time":0.4334380292},
{"learn":[3.845397429],"iteration":545,"passed_time":0.5197693528,"remaining_time":0.4321891688},
{"learn":[3.841933528],"iteration":546,"passed_time":0.5203677929,"remaining_time":0.4309444427},
{"learn":[3.840996474],"iteration":547,"passed_time":0.5211951603,"remaining_time":0.4298908986},
{"learn":[3.838355966],"iteration":548,"passed_time":0.5219914993,"remaining_time":0.4288126889},
{"learn":[3.83342799],"iteration":549,"passed_time":0.5226381758,"remaining_time":0.4276130529},
{"learn":[3.828161535],"iteration":550,"passed_time":0.5233113344,"remaining_time":0.4264370039},
{"learn":[3.823502399],"iteration":551,"passed_time":0.5239962698,"remaining_time":0.4252723349},
{"learn":[3.820068862],"iteration":552,"passed_time":0.5246186593,"remaining_time":0.424058844},
{"learn":[3.817951642],"iteration":553,"passed_time":0.5252436926,"remaining_time":0.4228496153},
{"learn":[3.815785958],"iteration":554,"passed_time":0.5258431617,"remaining_time":0.4216219946},
{"learn":[3.81503012],"iteration":555,"passed_time":0.5264523875,"remaining_time":0.4204044245},
{"learn":[3.813529315],"iteration":556,"passed_time":0.5273085291,"remaining_time":0.419385419},
{"learn":[3.808881326],"iteration":557,"passed_time":0.5281849225,"remaining_time":0.4183830389},
{"learn":[3.808740434],"iteration":558,"passed_time":0.529013904,"remaining_time":0.417343706},
{"learn":[3.80714352],"iteration":559,"passed_time":0.5296972881,"remaining_time":0.4161907264},
{"learn":[3.80573346],"iteration":560,"passed_time":0.5304436685,"remaining_time":0.4150887174},
{"learn":[3.803370052],"iteration":561,"passed_time":0.5310538512,"remaining_time":0.4138818271},
{"learn":[3.803215211],"iteration":562,"passed_time":0.531666419,"remaining_time":0.4126789079},
{"learn":[3.801309667],"iteration":563,"passed_time":0.5322642235,"remaining_time":0.4114666692},
{"learn":[3.800003847],"iteration":564,"passed_time":0.5330077111,"remaining_time":0.4103687687},
{"learn":[3.798026138],"iteration":565,"passed_time":0.5338918938,"remaining_time":0.4093800034},
{"learn":[3.794745847],"iteration":566,"passed_time":0.5347318612,"remaining_time":0.4083578411},
{"learn":[3.794312041],"iteration":567,"passed_time":0.5353818722,"remaining_time":0.4071918464},
{"learn":[3.792205926],"iteration":568,"passed_time":0.5360688021,"remaining_time":0.4060556304},
{"learn":[3.788991061],"iteration":569,"passed_time":0.5367656956,"remaining_time":0.4049285072},
{"learn":[3.787391572],"iteration":570,"passed_time":0.5374079226,"remaining_time":0.4037618193},
{"learn":[3.7826445],"iteration":571,"passed_time":0.5380487201,"remaining_time":0.4025958955},
{"learn":[3.781700331],"iteration":572,"passed_time":0.5387252154,"remaining_time":0.4014584066},
{"learn":[3.780045374],"iteration":573,"passed_time":0.5396892411,"remaining_time":0.4005359176},
{"learn":[3.775462644],"iteration":574,"passed_time":0.5405252341,"remaining_time":0.3995186513},
{"learn":[3.773711943],"iteration":575,"passed_time":0.5414299358,"remaining_time":0.3985525916},
{"learn":[3.772415806],"iteration":576,"passed_time":0.5422283349,"remaining_time":0.397508814},
{"learn":[3.770170875],"iteration":577,"passed_time":0.5428315007,"remaining_time":0.3963233448},
{"learn":[3.765166479],"iteration":578,"passed_time":0.5434614197,"remaining_time":0.3951593397},
{"learn":[3.763976102],"iteration":579,"passed_time":0.5441350774,"remaining_time":0.3940288491},
{"learn":[3.760761708],"iteration":580,"passed_time":0.5448709341,"remaining_time":0.3929447872},
{"learn":[3.758155662],"iteration":581,"passed_time":0.5457553803,"remaining_time":0.3919686408},
{"learn":[3.756844548],"iteration":582,"passed_time":0.5464780589,"remaining_time":0.3908771021},
{"learn":[3.753098923],"iteration":583,"passed_time":0.5471323913,"remaining_time":0.3897381418},
{"learn":[3.751618946],"iteration":584,"passed_time":0.547856887,"remaining_time":0.3886506121},
{"learn":[3.751398464],"iteration":585,"passed_time":0.5485049305,"remaining_time":0.3875103092},
{"learn":[3.749920103],"iteration":586,"passed_time":0.5490836624,"remaining_time":0.3863229175},
{"learn":[3.748237465],"iteration":587,"passed_time":0.5496777471,"remaining_time":0.3851483534},
{"learn":[3.746021536],"iteration":588,"passed_time":0.5502848734,"remaining_time":0.3839848607},
{"learn":[3.74417648],"iteration":589,"passed_time":0.5510154748,"remaining_time":0.3829090588},
{"learn":[3.738788389],"iteration":590,"passed_time":0.5519832881,"remaining_time":0.3819985869},
{"learn":[3.736021611],"iteration":591,"passed_time":0.552759379,"remaining_time":0.3809557882},
{"learn":[3.734546151],"iteration":592,"passed_time":0.5534814288,"remaining_time":0.3798767986},
{"learn":[3.733527479],"iteration":593,"passed_time":0.5541551941,"remaining_time":0.3787660081},
{"learn":[3.733026392],"iteration":594,"passed_time":0.5547698518,"remaining_time":0.3776164537},
{"learn":[3.730314752],"iteration":595,"passed_time":0.5553580837,"remaining_time":0.3764507816},
{"learn":[3.727342596],"iteration":596,"passed_time":0.5559605306,"remaining_time":0.3752966396},
{"learn":[3.725459604],"iteration":597,"passed_time":0.5565583906,"remaining_time":0.3741412592},
{"learn":[3.723158842],"iteration":598,"passed_time":0.5574169892,"remaining_time":0.3731622916},
{"learn":[3.722362756],"iteration":599,"passed_time":0.5581950572,"remaining_time":0.3721300381},
{"learn":[3.721443615],"iteration":600,"passed_time":0.5589484529,"remaining_time":0.3710822507},
{"learn":[3.720743486],"iteration":601,"passed_time":0.5595803394,"remaining_time":0.3699551081},
{"learn":[3.720215334],"iteration":602,"passed_time":0.560309155,"remaining_time":0.3688934238},
{"learn":[3.719436563],"iteration":603,"passed_time":0.5609076584,"remaining_time":0.3677474051},
{"learn":[3.715046574],"iteration":604,"passed_time":0.5614945627,"remaining_time":0.3665956236},
{"learn":[3.71443396],"iteration":605,"passed_time":0.5620728657,"remaining_time":0.365440114},
{"learn":[3.712938941],"iteration":606,"passed_time":0.5626634759,"remaining_time":0.3642944745},
{"learn":[3.712814764],"iteration":607,"passed_time":0.5635745507,"remaining_time":0.3633572761},
{"learn":[3.71235348],"iteration":608,"passed_time":0.5643761091,"remaining_time":0.36234985},
{"learn":[3.711223749],"iteration":609,"passed_time":0.5651849999,"remaining_time":0.3613477868},
{"learn":[3.710755648],"iteration":610,"passed_time":0.5658128522,"remaining_time":0.3602310958},
{"learn":[3.708668039],"iteration":611,"passed_time":0.5665102009,"remaining_time":0.359160062},
{"learn":[3.705623591],"iteration":612,"passed_time":0.567092881,"remaining_time":0.3580178547},
{"learn":[3.704045802],"iteration":613,"passed_time":0.5677068366,"remaining_time":0.3568971318},
{"learn":[3.699915209],"iteration":614,"passed_time":0.5683462992,"remaining_time":0.3557940247},
{"learn":[3.696182221],"iteration":615,"passed_time":0.5690182142,"remaining_time":0.354712653},
{"learn":[3.694263278],"iteration":616,"passed_time":0.5698872575,"remaining_time":0.3537549751},
{"learn":[3.693810229],"iteration":617,"passed_time":0.5707744719,"remaining_time":0.352808816},
{"learn":[3.690900932],"iteration":618,"passed_time":0.5716390421,"remaining_time":0.3518489096},
{"learn":[3.688020895],"iteration":619,"passed_time":0.5724308583,"remaining_time":0.3508447196},
{"learn":[3.685491894],"iteration":620,"passed_time":0.5731270988,"remaining_time":0.3497828832},
{"learn":[3.684328128],"iteration":621,"passed_time":0.5740104106,"remaining_time":0.3488359087},
{"learn":[3.680640153],"iteration":622,"passed_time":0.574771684,"remaining_time":0.3478152887},
{"learn":[3.678932783],"iteration":623,"passed_time":0.5757511041,"remaining_time":0.3469269474},
{"learn":[3.674167041],"iteration":624,"passed_time":0.5765811075,"remaining_time":0.3459486645},
{"learn":[3.672200976],"iteration":625,"passed_time":0.5772849279,"remaining_time":0.3448954681},
{"learn":[3.670606604],"iteration":626,"passed_time":0.5780295997,"remaining_time":0.3438676885},
{"learn":[3.665506042],"iteration":627,"passed_time":0.5787195123,"remaining_time":0.3428083735},
{"learn":[3.664214007],"iteration":628,"passed_time":0.579502775,"remaining_time":0.3418052933},
{"learn":[3.66261643],"iteration":629,"passed_time":0.5801349615,"remaining_time":0.3407141838},
{"learn":[3.662118449],"iteration":630,"passed_time":0.5807385678,"remaining_time":0.3396078154},
{"learn":[3.660871366],"iteration":631,"passed_time":0.5814533996,"remaining_time":0.3385678023},
{"learn":[3.656695243],"iteration":632,"passed_time":0.5824702898,"remaining_time":0.3377039437},
{"learn":[3.654497801],"iteration":633,"passed_time":0.5831635334,"remaining_time":0.3366527653},
{"learn":[3.654189134],"iteration":634,"passed_time":0.5838787307,"remaining_time":0.3356153334},
{"learn":[3.653957699],"iteration":635,"passed_time":0.5845159597,"remaining_time":0.3345342914},
{"learn":[3.651920725],"iteration":636,"passed_time":0.5851639665,"remaining_time":0.3334607847},
{"learn":[3.65106705],"iteration":637,"passed_time":0.5857565639,"remaining_time":0.3323571726},
{"learn":[3.650612844],"iteration":638,"passed_time":0.586346952,"remaining_time":0.3312539118},
{"learn":[3.649884732],"iteration":639,"passed_time":0.5869332338,"remaining_time":0.330149944},
{"learn":[3.646276182],"iteration":640,"passed_time":0.5877853305,"remaining_time":0.3291964644},
{"learn":[3.645808194],"iteration":641,"passed_time":0.5884906337,"remaining_time":0.3281614437},
{"learn":[3.645042989],"iteration":642,"passed_time":0.5892262621,"remaining_time":0.3271442855},
{"learn":[3.639864499],"iteration":643,"passed_time":0.5898870451,"remaining_time":0.3260866274},
{"learn":[3.637318478],"iteration":644,"passed_time":0.5905183831,"remaining_time":0.3250139938},
{"learn":[3.636344905],"iteration":645,"passed_time":0.5913501345,"remaining_time":0.3240525505},
{"learn":[3.634754643],"iteration":646,"passed_time":0.5919846839,"remaining_time":0.3229839157},
{"learn":[3.630724975],"iteration":647,"passed_time":0.5925898624,"remaining_time":0.321900666},
{"learn":[3.629408252],"iteration":648,"passed_time":0.5931828571,"remaining_time":0.3208123002},
{"learn":[3.62790646],"iteration":649,"passed_time":0.5942772436,"remaining_time":0.3199954389},
{"learn":[3.627388973],"iteration":650,"passed_time":0.5950927547,"remaining_time":0.3190282202},
{"learn":[3.625163557],"iteration":651,"passed_time":0.5958116197,"remaining_time":0.3180098829},
{"learn":[3.623701985],"iteration":652,"passed_time":0.596440706,"remaining_time":0.3169447549},
{"learn":[3.622342639],"iteration":653,"passed_time":0.597096594,"remaining_time":0.31589514},
{"learn":[3.621130639],"iteration":654,"passed_time":0.5977703446,"remaining_time":0.3148561357},
{"learn":[3.619125665],"iteration":655,"passed_time":0.598474994,"remaining_time":0.3138344481},
{"learn":[3.618878783],"iteration":656,"passed_time":0.5991156083,"remaining_time":0.3127802948},
{"learn":[3.616207429],"iteration":657,"passed_time":0.6000907131,"remaining_time":0.3119012521},
{"learn":[3.61206486],"iteration":658,"passed_time":0.600841859,"remaining_time":0.3109060302},
{"learn":[3.611955873],"iteration":659,"passed_time":0.6014984995,"remaining_time":0.3098628634},
{"learn":[3.610713743],"iteration":660,"passed_time":0.6022046177,"remaining_time":0.3088462411},
{"learn":[3.610044025],"iteration":661,"passed_time":0.6028271885,"remaining_time":0.3077878999},
{"learn":[3.607342669],"iteration":662,"passed_time":0.6035267724,"remaining_time":0.3067700186},
{"learn":[3.602510618],"iteration":663,"passed_time":0.6041214148,"remaining_time":0.305699993},
{"learn":[3.600492392],"iteration":664,"passed_time":0.604861264,"remaining_time":0.3047045465},
{"learn":[3.597171065],"iteration":665,"passed_time":0.6054541723,"remaining_time":0.3036361765},
{"learn":[3.594358798],"iteration":666,"passed_time":0.6066024841,"remaining_time":0.3028465175},
{"learn":[3.593945251],"iteration":667,"passed_time":0.6073673812,"remaining_time":0.3018652254},
{"learn":[3.593607748],"iteration":668,"passed_time":0.6080441596,"remaining_time":0.3008409818},
{"learn":[3.592238714],"iteration":669,"passed_time":0.6086860954,"remaining_time":0.2998006142},
{"learn":[3.590144654],"iteration":670,"passed_time":0.6094144304,"remaining_time":0.2988037967},
{"learn":[3.587151536],"iteration":671,"passed_time":0.6100199853,"remaining_time":0.29774785},
{"learn":[3.586070865],"iteration":672,"passed_time":0.6106020829,"remaining_time":0.2966818442},
{"learn":[3.585102746],"iteration":673,"passed_time":0.6112009057,"remaining_time":0.2956253639},
{"learn":[3.584362847],"iteration":674,"passed_time":0.6118516943,"remaining_time":0.2945952602},
{"learn":[3.581407561],"iteration":675,"passed_time":0.612894339,"remaining_time":0.2937540915},
{"learn":[3.57919422],"iteration":676,"passed_time":0.6136689835,"remaining_time":0.2927844633},
{"learn":[3.577632204],"iteration":677,"passed_time":0.6144151648,"remaining_time":0.2918018924},
{"learn":[3.573911195],"iteration":678,"passed_time":0.6150876546,"remaining_time":0.2907851798},
{"learn":[3.573408216],"iteration":679,"passed_time":0.61570031,"remaining_time":0.2897413224},
{"learn":[3.571076482],"iteration":680,"passed_time":0.6163131594,"remaining_time":0.2886988221},
{"learn":[3.568177107],"iteration":681,"passed_time":0.6169096857,"remaining_time":0.2876499707},
{"learn":[3.564824621],"iteration":682,"passed_time":0.6174999704,"remaining_time":0.286599547},
{"learn":[3.562475026],"iteration":683,"passed_time":0.6185036489,"remaining_time":0.2857414518},
{"learn":[3.561226889],"iteration":684,"passed_time":0.6193190157,"remaining_time":0.2847963357},
{"learn":[3.559383467],"iteration":685,"passed_time":0.6200908745,"remaining_time":0.2838316831},
{"learn":[3.555209766],"iteration":686,"passed_time":0.6207588171,"remaining_time":0.2828202471},
{"learn":[3.55345383],"iteration":687,"passed_time":0.6214446767,"remaining_time":0.2818179348},
{"learn":[3.552300968],"iteration":688,"passed_time":0.622084886,"remaining_time":0.2807959355},
{"learn":[3.551253986],"iteration":689,"passed_time":0.6226993122,"remaining_time":0.2797634591},
{"learn":[3.549807725],"iteration":690,"passed_time":0.6233494493,"remaining_time":0.2787481619},
{"learn":[3.547992926],"iteration":691,"passed_time":0.6240690021,"remaining_time":0.277764816},
{"learn":[3.545438607],"iteration":692,"passed_time":0.6250323841,"remaining_time":0.2768902481},
{"learn":[3.543313763],"iteration":693,"passed_time":0.6258093528,"remaining_time":0.2759332305},
{"learn":[3.542962896],"iteration":694,"passed_time":0.6265020467,"remaining_time":0.2749397471},
{"learn":[3.539800465],"iteration":695,"passed_time":0.6271416412,"remaining_time":0.2739239352},
{"learn":[3.53953187],"iteration":696,"passed_time":0.6278331938,"remaining_time":0.2729317901},
{"learn":[3.536332425],"iteration":697,"passed_time":0.6284492817,"remaining_time":0.2719078554},
{"learn":[3.534993327],"iteration":698,"passed_time":0.6290283955,"remaining_time":0.270869166},
{"learn":[3.531637011],"iteration":699,"passed_time":0.6296362199,"remaining_time":0.2698440942},
{"learn":[3.531040284],"iteration":700,"passed_time":0.6307083953,"remaining_time":0.2690182742},
{"learn":[3.529973872],"iteration":701,"passed_time":0.6315379956,"remaining_time":0.2680887788},
{"learn":[3.527325183],"iteration":702,"passed_time":0.6323297724,"remaining_time":0.2671435881},
{"learn":[3.527200815],"iteration":703,"passed_time":0.6329414053,"remaining_time":0.2661230909},
{"learn":[3.523459911],"iteration":704,"passed_time":0.6335985809,"remaining_time":0.2651228104},
{"learn":[3.522729934],"iteration":705,"passed_time":0.6342076781,"remaining_time":0.2641034807},
{"learn":[3.522260582],"iteration":706,"passed_time":0.6347884628,"remaining_time":0.2630735779},
{"learn":[3.518641591],"iteration":707,"passed_time":0.635382782,"remaining_time":0.2620505259},
{"learn":[3.516856405],"iteration":708,"passed_time":0.6359883817,"remaining_time":0.2610333132},
{"learn":[3.515083413],"iteration":709,"passed_time":0.6372406015,"remaining_time":0.2602813725},
{"learn":[3.514671214],"iteration":710,"passed_time":0.6379757347,"remaining_time":0.2593178443},
{"learn":[3.512617621],"iteration":711,"passed_time":0.6386115438,"remaining_time":0.2583147818},
{"learn":[3.510747971],"iteration":712,"passed_time":0.6392693727,"remaining_time":0.2573216129},
{"learn":[3.508149266],"iteration":713,"passed_time":0.6399417892,"remaining_time":0.2563352265},
{"learn":[3.504557165],"iteration":714,"passed_time":0.6405632075,"remaining_time":0.2553293904},
{"learn":[3.501367208],"iteration":715,"passed_time":0.641294811,"remaining_time":0.2543683329},
{"learn":[3.497593362],"iteration":716,"passed_time":0.6419044398,"remaining_time":0.2533597719},
{"learn":[3.496291169],"iteration":717,"passed_time":0.6429255046,"remaining_time":0.2525139168},
{"learn":[3.49330374],"iteration":718,"passed_time":0.6437524403,"remaining_time":0.2515917048},
{"learn":[3.490044385],"iteration":719,"passed_time":0.6445396037,"remaining_time":0.2506542903},
{"learn":[3.488891789],"iteration":720,"passed_time":0.6452457454,"remaining_time":0.2496859403},
{"learn":[3.486869081],"iteration":721,"passed_time":0.6459470935,"remaining_time":0.2487164709},
{"learn":[3.486303638],"iteration":722,"passed_time":0.6465898312,"remaining_time":0.247725288},
{"learn":[3.486035862],"iteration":723,"passed_time":0.6473271686,"remaining_time":0.2467711306},
{"learn":[3.482668951],"iteration":724,"passed_time":0.6480178927,"remaining_time":0.2457998904},
{"learn":[3.47820549],"iteration":725,"passed_time":0.6491422554,"remaining_time":0.2449930826},
{"learn":[3.474392283],"iteration":726,"passed_time":0.6501914854,"remaining_time":0.2441571878},
{"learn":[3.472268163],"iteration":727,"passed_time":0.6509823809,"remaining_time":0.2432241863},
{"learn":[3.471209164],"iteration":728,"passed_time":0.651933424,"remaining_time":0.2423511082},
{"learn":[3.470049971],"iteration":729,"passed_time":0.6527391265,"remaining_time":0.2414240605},
{"learn":[3.469078654],"iteration":730,"passed_time":0.6535892133,"remaining_time":0.2405136777},
{"learn":[3.468643292],"iteration":731,"passed_time":0.6543525699,"remaining_time":0.2395717059},
{"learn":[3.468134848],"iteration":732,"passed_time":0.6553892474,"remaining_time":0.2387297804},
{"learn":[3.467820182],"iteration":733,"passed_time":0.6562572805,"remaining_time":0.2378262079},
{"learn":[3.465776156],"iteration":734,"passed_time":0.6571431322,"remaining_time":0.2369291565},
{"learn":[3.463037608],"iteration":735,"passed_time":0.6579651112,"remaining_time":0.2360092247},
{"learn":[3.45965637],"iteration":736,"passed_time":0.658775858,"remaining_time":0.2350855504},
{"learn":[3.457275091],"iteration":737,"passed_time":0.6596396163,"remaining_time":0.234181002},
{"learn":[3.455522955],"iteration":738,"passed_time":0.6606157046,"remaining_time":0.2333162367},
{"learn":[3.451270508],"iteration":739,"passed_time":0.6619685124,"remaining_time":0.2325835314},
{"learn":[3.450978947],"iteration":740,"passed_time":0.6627842194,"remaining_time":0.2316614208},
{"learn":[3.450608492],"iteration":741,"passed_time":0.663393407,"remaining_time":0.2306677884},
{"learn":[3.448122004],"iteration":742,"passed_time":0.6641305304,"remaining_time":0.2297194432},
{"learn":[3.445646714],"iteration":743,"passed_time":0.6651062257,"remaining_time":0.2288537551},
{"learn":[3.44411263],"iteration":744,"passed_time":0.6659179113,"remaining_time":0.2279316341},
{"learn":[3.443264164],"iteration":745,"passed_time":0.66719781,"remaining_time":0.2271692275},
{"learn":[3.439521363],"iteration":746,"passed_time":0.6680216034,"remaining_time":0.226250958},
{"learn":[3.436809225],"iteration":747,"passed_time":0.6688908268,"remaining_time":0.2253482465},
{"learn":[3.435509465],"iteration":748,"passed_time":0.6696087947,"remaining_time":0.2243949365},
{"learn":[3.434450277],"iteration":749,"passed_time":0.6703370854,"remaining_time":0.2234456951},
{"learn":[3.431786753],"iteration":750,"passed_time":0.6710316384,"remaining_time":0.2224858562},
{"learn":[3.430150302],"iteration":751,"passed_time":0.6717379329,"remaining_time":0.2215305949},
{"learn":[3.42696281],"iteration":752,"passed_time":0.6727100071,"remaining_time":0.2206631763},
{"learn":[3.426870334],"iteration":753,"passed_time":0.6736866987,"remaining_time":0.2197969866},
{"learn":[3.425200309],"iteration":754,"passed_time":0.6744483008,"remaining_time":0.2188607069},
{"learn":[3.423383783],"iteration":755,"passed_time":0.6751204083,"remaining_time":0.2178960048},
{"learn":[3.422752979],"iteration":756,"passed_time":0.6757449,"remaining_time":0.2169167909},
{"learn":[3.420845924],"iteration":757,"passed_time":0.6764131334,"remaining_time":0.2159524779},
{"learn":[3.418917862],"iteration":758,"passed_time":0.6770096712,"remaining_time":0.2149661802},
{"learn":[3.417095735],"iteration":759,"passed_time":0.6776719909,"remaining_time":0.2140016813},
{"learn":[3.414391848],"iteration":760,"passed_time":0.6782952074,"remaining_time":0.2130256959},
{"learn":[3.41426711],"iteration":761,"passed_time":0.679191886,"remaining_time":0.2121360484},
{"learn":[3.411976013],"iteration":762,"passed_time":0.6800223587,"remaining_time":0.2112258178},
{"learn":[3.408614844],"iteration":763,"passed_time":0.680828902,"remaining_time":0.2103084043},
{"learn":[3.407906721],"iteration":764,"passed_time":0.6814732998,"remaining_time":0.2093414712},
{"learn":[3.407494015],"iteration":765,"passed_time":0.6821664354,"remaining_time":0.2083902688},
{"learn":[3.406287128],"iteration":766,"passed_time":0.6828397116,"remaining_time":0.2074337064},
{"learn":[3.404600442],"iteration":767,"passed_time":0.6835269793,"remaining_time":0.2064821083},
{"learn":[3.404012662],"iteration":768,"passed_time":0.6841137818,"remaining_time":0.205501019},
{"learn":[3.400398762],"iteration":769,"passed_time":0.6847987847,"remaining_time":0.2045502864},
{"learn":[3.399737714],"iteration":770,"passed_time":0.685994278,"remaining_time":0.2037518673},
{"learn":[3.399185251],"iteration":771,"passed_time":0.6867332651,"remaining_time":0.2028175964},
{"learn":[3.397245411],"iteration":772,"passed_time":0.6875100302,"remaining_time":0.2018949248},
{"learn":[3.396229831],"iteration":773,"passed_time":0.6882028429,"remaining_time":0.2009481169},
{"learn":[3.394002836],"iteration":774,"passed_time":0.6888175808,"remaining_time":0.1999792976},
{"learn":[3.389617243],"iteration":775,"passed_time":0.6894104775,"remaining_time":0.1990050863},
{"learn":[3.385426488],"iteration":776,"passed_time":0.6900353321,"remaining_time":0.1980410284},
{"learn":[3.385072258],"iteration":777,"passed_time":0.6905918094,"remaining_time":0.1970583312},
{"learn":[3.383842366],"iteration":778,"passed_time":0.6914594271,"remaining_time":0.1961649979},
{"learn":[3.380110746],"iteration":779,"passed_time":0.6922744911,"remaining_time":0.1952569077},
{"learn":[3.378595218],"iteration":780,"passed_time":0.6930499413,"remaining_time":0.1943379477},
{"learn":[3.377371219],"iteration":781,"passed_time":0.6938382058,"remaining_time":0.1934229269},
{"learn":[3.375814782],"iteration":782,"passed_time":0.6944401868,"remaining_time":0.1924566035},
{"learn":[3.374195887],"iteration":783,"passed_time":0.6950392548,"remaining_time":0.1914904069},
{"learn":[3.373704309],"iteration":784,"passed_time":0.6956189865,"remaining_time":0.1905198498},
{"learn":[3.372971757],"iteration":785,"passed_time":0.6962233457,"remaining_time":0.1895569923},
{"learn":[3.371565136],"iteration":786,"passed_time":0.6971356223,"remaining_time":0.1886783832},
{"learn":[3.3700309],"iteration":787,"passed_time":0.6980514278,"remaining_time":0.1878006379},
{"learn":[3.368186663],"iteration":788,"passed_time":0.6988327138,"remaining_time":0.1868868221},
{"learn":[3.366710398],"iteration":789,"passed_time":0.699536768,"remaining_time":0.1859528117},
{"learn":[3.364598042],"iteration":790,"passed_time":0.7001504405,"remaining_time":0.184995502},
{"learn":[3.36348442],"iteration":791,"passed_time":0.7007472776,"remaining_time":0.1840346386},
{"learn":[3.362001759],"iteration":792,"passed_time":0.7013358351,"remaining_time":0.183072532},
{"learn":[3.361580401],"iteration":793,"passed_time":0.7019770342,"remaining_time":0.182125024},
{"learn":[3.359543675],"iteration":794,"passed_time":0.7025874359,"remaining_time":0.1811703451},
{"learn":[3.35766119],"iteration":795,"passed_time":0.7036939954,"remaining_time":0.1803436873},
{"learn":[3.354592969],"iteration":796,"passed_time":0.7045297986,"remaining_time":0.179447364},
{"learn":[3.350985986],"iteration":797,"passed_time":0.7052704536,"remaining_time":0.1785271073},
{"learn":[3.349589624],"iteration":798,"passed_time":0.7058923298,"remaining_time":0.1775774196},
{"learn":[3.349110856],"iteration":799,"passed_time":0.706497789,"remaining_time":0.1766244473},
{"learn":[3.345315441],"iteration":800,"passed_time":0.7070884116,"remaining_time":0.1756686566},
{"learn":[3.34397474],"iteration":801,"passed_time":0.7076827671,"remaining_time":0.1747146981},
{"learn":[3.343800902],"iteration":802,"passed_time":0.708264064,"remaining_time":0.1737584316},
{"learn":[3.342329465],"iteration":803,"passed_time":0.7090332587,"remaining_time":0.1728489039},
{"learn":[3.34220347],"iteration":804,"passed_time":0.7099022776,"remaining_time":0.1719639058},
{"learn":[3.341279219],"iteration":805,"passed_time":0.7106847404,"remaining_time":0.1710581137},
{"learn":[3.337329521],"iteration":806,"passed_time":0.7115250911,"remaining_time":0.1701664716},
{"learn":[3.336708453],"iteration":807,"passed_time":0.7121253279,"remaining_time":0.1692178997},
{"learn":[3.333252703],"iteration":808,"passed_time":0.7127132073,"remaining_time":0.1682672714},
{"learn":[3.332186769],"iteration":809,"passed_time":0.7133239041,"remaining_time":0.1673228911},
{"learn":[3.330594851],"iteration":810,"passed_time":0.7139110707,"remaining_time":0.16637385},
{"learn":[3.327867442],"iteration":811,"passed_time":0.7145720316,"remaining_time":0.1654427856},
{"learn":[3.327563111],"iteration":812,"passed_time":0.7157164214,"remaining_time":0.1646235803},
{"learn":[3.326308994],"iteration":813,"passed_time":0.7164210388,"remaining_time":0.1637030875},
{"learn":[3.326249879],"iteration":814,"passed_time":0.7171121471,"remaining_time":0.1627800579},
{"learn":[3.322336238],"iteration":815,"passed_time":0.7177860018,"remaining_time":0.1618537063},
{"learn":[3.320491154],"iteration":816,"passed_time":0.7184774272,"remaining_time":0.1609319084},
{"learn":[3.320434271],"iteration":817,"passed_time":0.7190961564,"remaining_time":0.1599944993},
{"learn":[3.319609638],"iteration":818,"passed_time":0.7196898337,"remaining_time":0.159052332},
{"learn":[3.316182682],"iteration":819,"passed_time":0.7202822475,"remaining_time":0.1581107373},
{"learn":[3.313126612],"iteration":820,"passed_time":0.7208594875,"remaining_time":0.1571666849},
{"learn":[3.311222803],"iteration":821,"passed_time":0.7221014506,"remaining_time":0.1563674674},
{"learn":[3.309627335],"iteration":822,"passed_time":0.7229940063,"remaining_time":0.1554920281},
{"learn":[3.307974895],"iteration":823,"passed_time":0.7236787323,"remaining_time":0.1545721564},
{"learn":[3.307321505],"iteration":824,"passed_time":0.7242673422,"remaining_time":0.1536324665},
{"learn":[3.306759087],"iteration":825,"passed_time":0.7248948602,"remaining_time":0.1527018228},
{"learn":[3.30484037],"iteration":826,"passed_time":0.7254900681,"remaining_time":0.1517651533},
{"learn":[3.30201994],"iteration":827,"passed_time":0.7260754697,"remaining_time":0.1508272715},
{"learn":[3.299302297],"iteration":828,"passed_time":0.7266641174,"remaining_time":0.1498909096},
{"learn":[3.298132671],"iteration":829,"passed_time":0.7275030518,"remaining_time":0.1490066492},
{"learn":[3.296976183],"iteration":830,"passed_time":0.7283253267,"remaining_time":0.1481191098},
{"learn":[3.293144745],"iteration":831,"passed_time":0.7290007158,"remaining_time":0.1472020676},
{"learn":[3.290284404],"iteration":832,"passed_time":0.7296787501,"remaining_time":0.146286136},
{"learn":[3.288285745],"iteration":833,"passed_time":0.7302958435,"remaining_time":0.1453586451},
{"learn":[3.286662667],"iteration":834,"passed_time":0.7309047309,"remaining_time":0.1444302762},
{"learn":[3.285692682],"iteration":835,"passed_time":0.7314991141,"remaining_time":0.1434998262},
{"learn":[3.284565611],"iteration":836,"passed_time":0.7320899558,"remaining_time":0.1425694896},
{"learn":[3.283897383],"iteration":837,"passed_time":0.7327311857,"remaining_time":0.1416497042},
{"learn":[3.280712855],"iteration":838,"passed_time":0.7335844631,"remaining_time":0.1407712736},
{"learn":[3.280468341],"iteration":839,"passed_time":0.73434996,"remaining_time":0.1398761829},
{"learn":[3.277814895],"iteration":840,"passed_time":0.7351354205,"remaining_time":0.1389851746},
{"learn":[3.276316385],"iteration":841,"passed_time":0.7359686449,"remaining_time":0.1381033799},
{"learn":[3.27557063],"iteration":842,"passed_time":0.7365643534,"remaining_time":0.1371774656},
{"learn":[3.27499628],"iteration":843,"passed_time":0.7371868564,"remaining_time":0.1362572863},
{"learn":[3.273569958],"iteration":844,"passed_time":0.7377837668,"remaining_time":0.135333117},
{"learn":[3.269665595],"iteration":845,"passed_time":0.738361944,"remaining_time":0.1344063113},
{"learn":[3.267984685],"iteration":846,"passed_time":0.7389722918,"remaining_time":0.1334861401},
{"learn":[3.267702508],"iteration":847,"passed_time":0.7399515626,"remaining_time":0.1326328273},
{"learn":[3.266671924],"iteration":848,"passed_time":0.740786596,"remaining_time":0.1317535642},
{"learn":[3.265359825],"iteration":849,"passed_time":0.7415467416,"remaining_time":0.1308611897},
{"learn":[3.2618983],"iteration":850,"passed_time":0.7423689979,"remaining_time":0.1299800008},
{"learn":[3.260456253],"iteration":851,"passed_time":0.742978693,"remaining_time":0.1290620265},
{"learn":[3.258389147],"iteration":852,"passed_time":0.7435939077,"remaining_time":0.1281457262},
{"learn":[3.258108469],"iteration":853,"passed_time":0.7441909461,"remaining_time":0.1272270236},
{"learn":[3.256424936],"iteration":854,"passed_time":0.7447841383,"remaining_time":0.1263084211},
{"learn":[3.254817983],"iteration":855,"passed_time":0.7461260556,"remaining_time":0.1255165327},
{"learn":[3.253898449],"iteration":856,"passed_time":0.7470143507,"remaining_time":0.1246476688},
{"learn":[3.253023652],"iteration":857,"passed_time":0.7477524002,"remaining_time":0.1237538937},
{"learn":[3.252845542],"iteration":858,"passed_time":0.7483884053,"remaining_time":0.1228437313},
{"learn":[3.252316026],"iteration":859,"passed_time":0.7489944593,"remaining_time":0.1219293306},
{"learn":[3.24975301],"iteration":860,"passed_time":0.749571292,"remaining_time":0.1210109287},
{"learn":[3.249151075],"iteration":861,"passed_time":0.7501955137,"remaining_time":0.1201009059},
{"learn":[3.246257135],"iteration":862,"passed_time":0.7508032633,"remaining_time":0.1191889306},
{"learn":[3.243826471],"iteration":863,"passed_time":0.751601149,"remaining_time":0.1183075883},
{"learn":[3.243190653],"iteration":864,"passed_time":0.7524751482,"remaining_time":0.1174383179},
{"learn":[3.24008797],"iteration":865,"passed_time":0.7532364336,"remaining_time":0.116551596},
{"learn":[3.240036811],"iteration":866,"passed_time":0.7541894639,"remaining_time":0.1156945775},
{"learn":[3.238676314],"iteration":867,"passed_time":0.7548360305,"remaining_time":0.1147907327},
{"learn":[3.237848782],"iteration":868,"passed_time":0.7554397988,"remaining_time":0.1138810284},
{"learn":[3.236405498],"iteration":869,"passed_time":0.7560266252,"remaining_time":0.1129694957},
{"learn":[3.233378068],"iteration":870,"passed_time":0.7566228328,"remaining_time":0.1120600981},
{"learn":[3.233169169],"iteration":871,"passed_time":0.757176577,"remaining_time":0.1111451856},
{"learn":[3.232434885],"iteration":872,"passed_time":0.7581618618,"remaining_time":0.1102938791},
{"learn":[3.229978115],"iteration":873,"passed_time":0.7588718336,"remaining_time":0.1094025756},
{"learn":[3.229648848],"iteration":874,"passed_time":0.7596864028,"remaining_time":0.108526629},
{"learn":[3.227208761],"iteration":875,"passed_time":0.7604619721,"remaining_time":0.107645302},
{"learn":[3.226258869],"iteration":876,"passed_time":0.7612029256,"remaining_time":0.1067593613},
{"learn":[3.225331995],"iteration":877,"passed_time":0.7619042988,"remaining_time":0.1058682511},
{"learn":[3.221968268],"iteration":878,"passed_time":0.7625977622,"remaining_time":0.1049764838},
{"learn":[3.221166317],"iteration":879,"passed_time":0.7632834374,"remaining_time":0.1040841051},
{"learn":[3.220047503],"iteration":880,"passed_time":0.7648327069,"remaining_time":0.1033088446},
{"learn":[3.21982781],"iteration":881,"passed_time":0.765570879,"remaining_time":0.1024233149},
{"learn":[3.216693405],"iteration":882,"passed_time":0.7662279956,"remaining_time":0.1015273788},
{"learn":[3.214798761],"iteration":883,"passed_time":0.7669401088,"remaining_time":0.1006391998},
{"learn":[3.214395085],"iteration":884,"passed_time":0.7676981851,"remaining_time":0.09975739128},
{"learn":[3.213470696],"iteration":885,"passed_time":0.7683033874,"remaining_time":0.09885619206},
{"learn":[3.211595017],"iteration":886,"passed_time":0.7688833583,"remaining_time":0.09795244587},
{"learn":[3.210965255],"iteration":887,"passed_time":0.7694763823,"remaining_time":0.09705107524},
{"learn":[3.209413583],"iteration":888,"passed_time":0.7704341861,"remaining_time":0.09619594449},
{"learn":[3.208331683],"iteration":889,"passed_time":0.7712078269,"remaining_time":0.0953178213},
{"learn":[3.207110711],"iteration":890,"passed_time":0.7719311928,"remaining_time":0.09443378228},
{"learn":[3.204519413],"iteration":891,"passed_time":0.7726530853,"remaining_time":0.09354992512},
{"learn":[3.201421296],"iteration":892,"passed_time":0.773281252,"remaining_time":0.09265520041},
{"learn":[3.200691259],"iteration":893,"passed_time":0.7739937502,"remaining_time":0.09177107105},
{"learn":[3.200485067],"iteration":894,"passed_time":0.7745898869,"remaining_time":0.09087367388},
{"learn":[3.197467568],"iteration":895,"passed_time":0.775182971,"remaining_time":0.08997659485},
{"learn":[3.195838544],"iteration":896,"passed_time":0.7758819509,"remaining_time":0.08909235333},
{"learn":[3.195671746],"iteration":897,"passed_time":0.7769363976,"remaining_time":0.08824890039},
{"learn":[3.194213094],"iteration":898,"passed_time":0.7776293985,"remaining_time":0.08736437069},
{"learn":[3.192884691],"iteration":899,"passed_time":0.77844003,"remaining_time":0.08649333667},
{"learn":[3.188364239],"iteration":900,"passed_time":0.7793037447,"remaining_time":0.08562826939},
{"learn":[3.185219478],"iteration":901,"passed_time":0.7799880502,"remaining_time":0.08474371277},
{"learn":[3.184120387],"iteration":902,"passed_time":0.7805788965,"remaining_time":0.08384956031},
{"learn":[3.183725321],"iteration":903,"passed_time":0.781154434,"remaining_time":0.08295445317},
{"learn":[3.181264554],"iteration":904,"passed_time":0.7817476192,"remaining_time":0.08206190478},
{"learn":[3.180741589],"iteration":905,"passed_time":0.7829014963,"remaining_time":0.08122819057},
{"learn":[3.179782639],"iteration":906,"passed_time":0.7837069936,"remaining_time":0.08035804896},
{"learn":[3.176377564],"iteration":907,"passed_time":0.7844779252,"remaining_time":0.07948454749},
{"learn":[3.174078182],"iteration":908,"passed_time":0.7850881642,"remaining_time":0.07859518475},
{"learn":[3.171242379],"iteration":909,"passed_time":0.7856973216,"remaining_time":0.07770632851},
{"learn":[3.170421012],"iteration":910,"passed_time":0.7863090332,"remaining_time":0.07681833584},
{"learn":[3.170087224],"iteration":911,"passed_time":0.7871008239,"remaining_time":0.07594832512},
{"learn":[3.167303059],"iteration":912,"passed_time":0.7880555567,"remaining_time":0.07509401252},
{"learn":[3.16705966],"iteration":913,"passed_time":0.7891147234,"remaining_time":0.07424930657},
{"learn":[3.165667683],"iteration":914,"passed_time":0.7899802763,"remaining_time":0.07338614589},
{"learn":[3.164689733],"iteration":915,"passed_time":0.79074979,"remaining_time":0.07251417289},
{"learn":[3.163311455],"iteration":916,"passed_time":0.7914419382,"remaining_time":0.0716354208},
{"learn":[3.159425016],"iteration":917,"passed_time":0.792046552,"remaining_time":0.07074925628},
{"learn":[3.159327058],"iteration":918,"passed_time":0.792638982,"remaining_time":0.06986263062},
{"learn":[3.15819426],"iteration":919,"passed_time":0.7932418593,"remaining_time":0.06897755298},
{"learn":[3.157086603],"iteration":920,"passed_time":0.7938531894,"remaining_time":0.06809381321},
{"learn":[3.153354154],"iteration":921,"passed_time":0.7950036442,"remaining_time":0.06725627359},
{"learn":[3.153261317],"iteration":922,"passed_time":0.7957817978,"remaining_time":0.06638699721},
{"learn":[3.153168454],"iteration":923,"passed_time":0.7965808452,"remaining_time":0.06551963662},
{"learn":[3.152080399],"iteration":924,"passed_time":0.7974617683,"remaining_time":0.0646590623},
{"learn":[3.151635144],"iteration":925,"passed_time":0.7982096653,"remaining_time":0.06378781343},
{"learn":[3.147762655],"iteration":926,"passed_time":0.7988423888,"remaining_time":0.06290776093},
{"learn":[3.147172317],"iteration":927,"passed_time":0.7995060412,"remaining_time":0.06203064113},
{"learn":[3.146254125],"iteration":928,"passed_time":0.8003321165,"remaining_time":0.06116639426},
{"learn":[3.144869828],"iteration":929,"passed_time":0.8012642579,"remaining_time":0.06031021296},
{"learn":[3.143466218],"iteration":930,"passed_time":0.8021124208,"remaining_time":0.0594476445},
{"learn":[3.141919643],"iteration":931,"passed_time":0.8028354341,"remaining_time":0.05857597588},
{"learn":[3.141054135],"iteration":932,"passed_time":0.8034806315,"remaining_time":0.05769903784},
{"learn":[3.139390417],"iteration":933,"passed_time":0.8041267383,"remaining_time":0.05682266031},
{"learn":[3.139025283],"iteration":934,"passed_time":0.8047052403,"remaining_time":0.05594207553},
{"learn":[3.137824183],"iteration":935,"passed_time":0.8052950406,"remaining_time":0.05506290876},
{"learn":[3.135620453],"iteration":936,"passed_time":0.8059021113,"remaining_time":0.05418552083},
{"learn":[3.13443178],"iteration":937,"passed_time":0.8069164177,"remaining_time":0.05333562675},
{"learn":[3.132765713],"iteration":938,"passed_time":0.8077317529,"remaining_time":0.05247245679},
{"learn":[3.131434124],"iteration":939,"passed_time":0.8085065184,"remaining_time":0.05160679905},
{"learn":[3.128384262],"iteration":940,"passed_time":0.8091529538,"remaining_time":0.05073328829},
{"learn":[3.128120455],"iteration":941,"passed_time":0.8097252105,"remaining_time":0.04985569236},
{"learn":[3.126314615],"iteration":942,"passed_time":0.8103340555,"remaining_time":0.04898095563},
{"learn":[3.125409666],"iteration":943,"passed_time":0.8109427886,"remaining_time":0.0481067756},
{"learn":[3.123072589],"iteration":944,"passed_time":0.8115521783,"remaining_time":0.04723319556},
{"learn":[3.122921099],"iteration":945,"passed_time":0.8121949877,"remaining_time":0.04636208175},
{"learn":[3.122182662],"iteration":946,"passed_time":0.8132765806,"remaining_time":0.04551600715},
{"learn":[3.120040951],"iteration":947,"passed_time":0.8139378103,"remaining_time":0.04464637778},
{"learn":[3.118767799],"iteration":948,"passed_time":0.8147018389,"remaining_time":0.0437827121},
{"learn":[3.118203218],"iteration":949,"passed_time":0.8153505747,"remaining_time":0.04291318814},
{"learn":[3.116343362],"iteration":950,"passed_time":0.8159769907,"remaining_time":0.04204297849},
{"learn":[3.11480829],"iteration":951,"passed_time":0.816591727,"remaining_time":0.04117269212},
{"learn":[3.112607903],"iteration":952,"passed_time":0.8171942587,"remaining_time":0.04030234015},
{"learn":[3.111661241],"iteration":953,"passed_time":0.8178181155,"remaining_time":0.0394335779},
{"learn":[3.110249676],"iteration":954,"passed_time":0.8187136454,"remaining_time":0.03857812989},
{"learn":[3.107333579],"iteration":955,"passed_time":0.8197473703,"remaining_time":0.03772895847},
{"learn":[3.107149851],"iteration":956,"passed_time":0.8203919594,"remaining_time":0.03686191667},
{"learn":[3.106867336],"iteration":957,"passed_time":0.8211552701,"remaining_time":0.0360005442},
{"learn":[3.10364681],"iteration":958,"passed_time":0.8217804163,"remaining_time":0.03513346931},
{"learn":[3.102703811],"iteration":959,"passed_time":0.8223841978,"remaining_time":0.03426600824},
{"learn":[3.101469264],"iteration":960,"passed_time":0.822971828,"remaining_time":0.03339844047},
{"learn":[3.09863569],"iteration":961,"passed_time":0.8235709786,"remaining_time":0.03253190976},
{"learn":[3.09645939],"iteration":962,"passed_time":0.8241819905,"remaining_time":0.03166639008},
{"learn":[3.096240186],"iteration":963,"passed_time":0.8253931239,"remaining_time":0.03082380961},
{"learn":[3.094838828],"iteration":964,"passed_time":0.826064328,"remaining_time":0.02996088236},
{"learn":[3.094176802],"iteration":965,"passed_time":0.8267066881,"remaining_time":0.02909733685},
{"learn":[3.093182279],"iteration":966,"passed_time":0.8274146191,"remaining_time":0.02823648648},
{"learn":[3.090150687],"iteration":967,"passed_time":0.8280064003,"remaining_time":0.02737211241},
{"learn":[3.088612829],"iteration":968,"passed_time":0.8285880952,"remaining_time":0.02650797828},
{"learn":[3.087153684],"iteration":969,"passed_time":0.8292144653,"remaining_time":0.02564580821},
{"learn":[3.085866843],"iteration":970,"passed_time":0.8298056464,"remaining_time":0.02478307286},
{"learn":[3.082669094],"iteration":971,"passed_time":0.8304666096,"remaining_time":0.02392290645},
{"learn":[3.081047548],"iteration":972,"passed_time":0.8317688139,"remaining_time":0.02308094345},
{"learn":[3.079684322],"iteration":973,"passed_time":0.8325611678,"remaining_time":0.02222442542},
{"learn":[3.07613431],"iteration":974,"passed_time":0.8332988381,"remaining_time":0.02136663687},
{"learn":[3.074005935],"iteration":975,"passed_time":0.8339106392,"remaining_time":0.02050599932},
{"learn":[3.072988853],"iteration":976,"passed_time":0.8345197341,"remaining_time":0.01964580746},
{"learn":[3.072344268],"iteration":977,"passed_time":0.8350889375,"remaining_time":0.01878523172},
{"learn":[3.070654438],"iteration":978,"passed_time":0.8356761218,"remaining_time":0.01792563693},
{"learn":[3.069724506],"iteration":979,"passed_time":0.8362811715,"remaining_time":0.01706696268},
{"learn":[3.067763166],"iteration":980,"passed_time":0.83723223,"remaining_time":0.016215507},
{"learn":[3.066737893],"iteration":981,"passed_time":0.8380525875,"remaining_time":0.01536145272},
{"learn":[3.065248174],"iteration":982,"passed_time":0.8387424638,"remaining_time":0.01450521046},
{"learn":[3.063186837],"iteration":983,"passed_time":0.8395080981,"remaining_time":0.01365053818},
{"learn":[3.062880371],"iteration":984,"passed_time":0.8401276249,"remaining_time":0.0127938217},
{"learn":[3.061288645],"iteration":985,"passed_time":0.8407372745,"remaining_time":0.01193744609},
{"learn":[3.059970575],"iteration":986,"passed_time":0.8413374172,"remaining_time":0.01108144521},
{"learn":[3.059576341],"iteration":987,"passed_time":0.8419242498,"remaining_time":0.0102258006},
{"learn":[3.058175919],"iteration":988,"passed_time":0.8427476964,"remaining_time":0.009373331305},
{"learn":[3.056830702],"iteration":989,"passed_time":0.8439127498,"remaining_time":0.008524371211},
{"learn":[3.056336579],"iteration":990,"passed_time":0.8446345074,"remaining_time":0.007670747292},
{"learn":[3.055810414],"iteration":991,"passed_time":0.8454010519,"remaining_time":0.006817750418},
{"learn":[3.055476518],"iteration":992,"passed_time":0.8461075342,"remaining_time":0.005964504269},
{"learn":[3.053331734],"iteration":993,"passed_time":0.8467802152,"remaining_time":0.005111349387},
{"learn":[3.050890374],"iteration":994,"passed_time":0.8473973637,"remaining_time":0.00425827821},
{"learn":[3.04972623],"iteration":995,"passed_time":0.847997727,"remaining_time":0.003405613361},
{"learn":[3.047217327],"iteration":996,"passed_time":0.8486174776,"remaining_time":0.002553512972},
{"learn":[3.047155483],"iteration":997,"passed_time":0.8495836135,"remaining_time":0.001702572372},
{"learn":[3.04430671],"iteration":998,"passed_time":0.8504524392,"remaining_time":0.0008513037429},
{"learn":[3.042664195],"iteration":999,"passed_time":0.8512248955,"remaining_time":0}
]}